{"_":[],"open":false,"o":false,"version":false,"v":false,"help":false,"h":false,"quiet":false,"q":false,"silent":false,"s":false,"treeDebug":false,"tree-debug":false,"kernelTracingDebug":false,"kernel-tracing-debug":false,"kernelTracing":false,"kernel-tracing":false,"collectOnly":false,"collect-only":false,"writeTicks":false,"write-ticks":false,"--":["index.js"],"workingDir":"/home/halister/Documentos/async-se-coda/javascript-expert/modulo12/02-memory-leak/02-leak-events","argv":["index.js"],"pathToNodeBinary":"/home/halister/.nvm/versions/node/v20.0.0/bin/node","name":"flamegraph","collectDelay":0,"title":"node index.js","pid":44809,"inlined":{"newAsyncId node:internal/async_hooks":[{"file":"node:internal/async_hooks","fn":"newAsyncId","id":"0","ix":"0","pos":"14568","caller":{"file":"node:internal/timers","fn":"initAsyncResource","id":"0","ix":"-1","pos":"5574","key":"initAsyncResource node:internal/timers"}},{"file":"node:internal/async_hooks","fn":"newAsyncId","id":"4","ix":"1","pos":"14568","caller":{"file":"node:internal/timers","fn":"Timeout","id":"4","ix":"-1","pos":"5943","key":"Timeout node:internal/timers"}},{"file":"node:internal/async_hooks","fn":"newAsyncId","id":"6","ix":"6","pos":"14568","caller":{"file":"file:///home/halister/Documentos/async-se-coda/javascript-expert/modulo12/02-memory-leak/02-leak-events/index.js","fn":"onData","id":"6","ix":"-1","pos":"109","key":"onData file:///home/halister/Documentos/async-se-coda/javascript-expert/modulo12/02-memory-leak/02-leak-events/index.js"}},{"file":"node:internal/async_hooks","fn":"newAsyncId","id":"7","ix":"5","pos":"14568","caller":{"file":"node:timers","fn":"setInterval","id":"7","ix":"-1","pos":"5812","key":"setInterval node:timers"}},{"file":"node:internal/async_hooks","fn":"newAsyncId","id":"14","ix":"2","pos":"14568","caller":{"file":"node:internal/process/task_queues","fn":"nextTick","id":"14","ix":"-1","pos":"2585","key":"nextTick node:internal/process/task_queues"}},{"file":"node:internal/async_hooks","fn":"newAsyncId","id":"22","ix":"4","pos":"14568","caller":{"file":"node:internal/streams/readable","fn":"endReadable","id":"22","ix":"-1","pos":"39631","key":"endReadable node:internal/streams/readable"}},{"file":"node:internal/async_hooks","fn":"newAsyncId","id":"27","ix":"5","pos":"14568","caller":{"file":"node:internal/streams/readable","fn":"Readable.resume","id":"27","ix":"-1","pos":"31274","key":"Readable.resume node:internal/streams/readable"}},{"file":"node:internal/async_hooks","fn":"newAsyncId","id":"43","ix":"1","pos":"14568","caller":{"file":"node:internal/timers","fn":"Timeout","id":"43","ix":"-1","pos":"5943","key":"Timeout node:internal/timers"}},{"file":"node:internal/async_hooks","fn":"newAsyncId","id":"44","ix":"5","pos":"14568","caller":{"file":"node:timers","fn":"setInterval","id":"44","ix":"-1","pos":"5812","key":"setInterval node:timers"}},{"file":"node:internal/async_hooks","fn":"newAsyncId","id":"59","ix":"5","pos":"14568","caller":{"file":"node:internal/streams/readable","fn":"Readable.resume","id":"59","ix":"-1","pos":"31274","key":"Readable.resume node:internal/streams/readable"}},{"file":"node:internal/async_hooks","fn":"newAsyncId","id":"79","ix":"6","pos":"14568","caller":{"file":"node:net","fn":"Socket.resume","id":"79","ix":"-1","pos":"19778","key":"Socket.resume node:net"}},{"file":"node:internal/async_hooks","fn":"newAsyncId","id":"94","ix":"5","pos":"14568","caller":{"file":"node:_http_server","fn":"resOnFinish","id":"94","ix":"-1","pos":"30286","key":"resOnFinish node:_http_server"}},{"file":"node:internal/async_hooks","fn":"newAsyncId","id":"97","ix":"4","pos":"14568","caller":{"file":"node:internal/streams/readable","fn":"emitReadable","id":"97","ix":"-1","pos":"18612","key":"emitReadable node:internal/streams/readable"}}],"initHooksExist node:internal/async_hooks":[{"file":"node:internal/async_hooks","fn":"initHooksExist","id":"0","ix":"1","pos":"16248","caller":{"file":"node:internal/timers","fn":"initAsyncResource","id":"0","ix":"-1","pos":"5574","key":"initAsyncResource node:internal/timers"}},{"file":"node:internal/async_hooks","fn":"initHooksExist","id":"4","ix":"2","pos":"16248","caller":{"file":"node:internal/timers","fn":"Timeout","id":"4","ix":"-1","pos":"5943","key":"Timeout node:internal/timers"}},{"file":"node:internal/async_hooks","fn":"initHooksExist","id":"6","ix":"7","pos":"16248","caller":{"file":"file:///home/halister/Documentos/async-se-coda/javascript-expert/modulo12/02-memory-leak/02-leak-events/index.js","fn":"onData","id":"6","ix":"-1","pos":"109","key":"onData file:///home/halister/Documentos/async-se-coda/javascript-expert/modulo12/02-memory-leak/02-leak-events/index.js"}},{"file":"node:internal/async_hooks","fn":"initHooksExist","id":"7","ix":"6","pos":"16248","caller":{"file":"node:timers","fn":"setInterval","id":"7","ix":"-1","pos":"5812","key":"setInterval node:timers"}},{"file":"node:internal/async_hooks","fn":"initHooksExist","id":"14","ix":"3","pos":"16248","caller":{"file":"node:internal/process/task_queues","fn":"nextTick","id":"14","ix":"-1","pos":"2585","key":"nextTick node:internal/process/task_queues"}},{"file":"node:internal/async_hooks","fn":"initHooksExist","id":"22","ix":"5","pos":"16248","caller":{"file":"node:internal/streams/readable","fn":"endReadable","id":"22","ix":"-1","pos":"39631","key":"endReadable node:internal/streams/readable"}},{"file":"node:internal/async_hooks","fn":"initHooksExist","id":"27","ix":"6","pos":"16248","caller":{"file":"node:internal/streams/readable","fn":"Readable.resume","id":"27","ix":"-1","pos":"31274","key":"Readable.resume node:internal/streams/readable"}},{"file":"node:internal/async_hooks","fn":"initHooksExist","id":"43","ix":"2","pos":"16248","caller":{"file":"node:internal/timers","fn":"Timeout","id":"43","ix":"-1","pos":"5943","key":"Timeout node:internal/timers"}},{"file":"node:internal/async_hooks","fn":"initHooksExist","id":"44","ix":"6","pos":"16248","caller":{"file":"node:timers","fn":"setInterval","id":"44","ix":"-1","pos":"5812","key":"setInterval node:timers"}},{"file":"node:internal/async_hooks","fn":"initHooksExist","id":"59","ix":"6","pos":"16248","caller":{"file":"node:internal/streams/readable","fn":"Readable.resume","id":"59","ix":"-1","pos":"31274","key":"Readable.resume node:internal/streams/readable"}},{"file":"node:internal/async_hooks","fn":"initHooksExist","id":"79","ix":"7","pos":"16248","caller":{"file":"node:net","fn":"Socket.resume","id":"79","ix":"-1","pos":"19778","key":"Socket.resume node:net"}},{"file":"node:internal/async_hooks","fn":"initHooksExist","id":"94","ix":"6","pos":"16248","caller":{"file":"node:_http_server","fn":"resOnFinish","id":"94","ix":"-1","pos":"30286","key":"resOnFinish node:_http_server"}},{"file":"node:internal/async_hooks","fn":"initHooksExist","id":"97","ix":"5","pos":"16248","caller":{"file":"node:internal/streams/readable","fn":"emitReadable","id":"97","ix":"-1","pos":"18612","key":"emitReadable node:internal/streams/readable"}}],"hasHooks node:internal/async_hooks":[{"file":"node:internal/async_hooks","fn":"hasHooks","id":"0","ix":"2","pos":"16116","caller":{"file":"node:internal/timers","fn":"initAsyncResource","id":"0","ix":"-1","pos":"5574","key":"initAsyncResource node:internal/timers"}},{"file":"node:internal/async_hooks","fn":"hasHooks","id":"4","ix":"3","pos":"16116","caller":{"file":"node:internal/timers","fn":"Timeout","id":"4","ix":"-1","pos":"5943","key":"Timeout node:internal/timers"}},{"file":"node:internal/async_hooks","fn":"hasHooks","id":"6","ix":"8","pos":"16116","caller":{"file":"file:///home/halister/Documentos/async-se-coda/javascript-expert/modulo12/02-memory-leak/02-leak-events/index.js","fn":"onData","id":"6","ix":"-1","pos":"109","key":"onData file:///home/halister/Documentos/async-se-coda/javascript-expert/modulo12/02-memory-leak/02-leak-events/index.js"}},{"file":"node:internal/async_hooks","fn":"hasHooks","id":"7","ix":"7","pos":"16116","caller":{"file":"node:timers","fn":"setInterval","id":"7","ix":"-1","pos":"5812","key":"setInterval node:timers"}},{"file":"node:internal/async_hooks","fn":"hasHooks","id":"15","ix":"1","pos":"16116","caller":{"file":"node:internal/async_hooks","fn":"popAsyncContext","id":"15","ix":"-1","pos":"18196","key":"popAsyncContext node:internal/async_hooks"}},{"file":"node:internal/async_hooks","fn":"hasHooks","id":"14","ix":"4","pos":"16116","caller":{"file":"node:internal/process/task_queues","fn":"nextTick","id":"14","ix":"-1","pos":"2585","key":"nextTick node:internal/process/task_queues"}},{"file":"node:internal/async_hooks","fn":"hasHooks","id":"17","ix":"0","pos":"16116","caller":{"file":"node:internal/async_hooks","fn":"emitBeforeScript","id":"17","ix":"-1","pos":"16918","key":"emitBeforeScript node:internal/async_hooks"}},{"file":"node:internal/async_hooks","fn":"hasHooks","id":"19","ix":"1","pos":"16116","caller":{"file":"node:internal/process/task_queues","fn":"processTicksAndRejections","id":"19","ix":"-1","pos":"1479","key":"processTicksAndRejections node:internal/process/task_queues"}},{"file":"node:internal/async_hooks","fn":"hasHooks","id":"19","ix":"1","pos":"16116","caller":{"file":"node:internal/process/task_queues","fn":"processTicksAndRejections","id":"19","ix":"-1","pos":"1479","key":"processTicksAndRejections node:internal/process/task_queues"}},{"file":"node:internal/async_hooks","fn":"hasHooks","id":"19","ix":"1","pos":"16116","caller":{"file":"node:internal/process/task_queues","fn":"processTicksAndRejections","id":"19","ix":"-1","pos":"1479","key":"processTicksAndRejections node:internal/process/task_queues"}},{"file":"node:internal/async_hooks","fn":"hasHooks","id":"19","ix":"1","pos":"16116","caller":{"file":"node:internal/process/task_queues","fn":"processTicksAndRejections","id":"19","ix":"-1","pos":"1479","key":"processTicksAndRejections node:internal/process/task_queues"}},{"file":"node:internal/async_hooks","fn":"hasHooks","id":"22","ix":"6","pos":"16116","caller":{"file":"node:internal/streams/readable","fn":"endReadable","id":"22","ix":"-1","pos":"39631","key":"endReadable node:internal/streams/readable"}},{"file":"node:internal/async_hooks","fn":"hasHooks","id":"27","ix":"7","pos":"16116","caller":{"file":"node:internal/streams/readable","fn":"Readable.resume","id":"27","ix":"-1","pos":"31274","key":"Readable.resume node:internal/streams/readable"}},{"file":"node:internal/async_hooks","fn":"hasHooks","id":"31","ix":"0","pos":"16116","caller":{"file":"node:internal/async_hooks","fn":"emitAfterScript","id":"31","ix":"-1","pos":"17096","key":"emitAfterScript node:internal/async_hooks"}},{"file":"node:internal/async_hooks","fn":"hasHooks","id":"31","ix":"0","pos":"16116","caller":{"file":"node:internal/async_hooks","fn":"emitAfterScript","id":"31","ix":"-1","pos":"17096","key":"emitAfterScript node:internal/async_hooks"}},{"file":"node:internal/async_hooks","fn":"hasHooks","id":"38","ix":"2","pos":"16116","caller":{"file":"node:internal/timers","fn":"listOnTimeout","id":"38","ix":"-1","pos":"15529","key":"listOnTimeout node:internal/timers"}},{"file":"node:internal/async_hooks","fn":"hasHooks","id":"38","ix":"2","pos":"16116","caller":{"file":"node:internal/timers","fn":"listOnTimeout","id":"38","ix":"-1","pos":"15529","key":"listOnTimeout node:internal/timers"}},{"file":"node:internal/async_hooks","fn":"hasHooks","id":"38","ix":"2","pos":"16116","caller":{"file":"node:internal/timers","fn":"listOnTimeout","id":"38","ix":"-1","pos":"15529","key":"listOnTimeout node:internal/timers"}},{"file":"node:internal/async_hooks","fn":"hasHooks","id":"43","ix":"3","pos":"16116","caller":{"file":"node:internal/timers","fn":"Timeout","id":"43","ix":"-1","pos":"5943","key":"Timeout node:internal/timers"}},{"file":"node:internal/async_hooks","fn":"hasHooks","id":"44","ix":"7","pos":"16116","caller":{"file":"node:timers","fn":"setInterval","id":"44","ix":"-1","pos":"5812","key":"setInterval node:timers"}},{"file":"node:internal/async_hooks","fn":"hasHooks","id":"59","ix":"7","pos":"16116","caller":{"file":"node:internal/streams/readable","fn":"Readable.resume","id":"59","ix":"-1","pos":"31274","key":"Readable.resume node:internal/streams/readable"}},{"file":"node:internal/async_hooks","fn":"hasHooks","id":"79","ix":"8","pos":"16116","caller":{"file":"node:net","fn":"Socket.resume","id":"79","ix":"-1","pos":"19778","key":"Socket.resume node:net"}},{"file":"node:internal/async_hooks","fn":"hasHooks","id":"85","ix":"2","pos":"16116","caller":{"file":"node:internal/timers","fn":"listOnTimeout","id":"85","ix":"-1","pos":"15529","key":"listOnTimeout node:internal/timers"}},{"file":"node:internal/async_hooks","fn":"hasHooks","id":"85","ix":"2","pos":"16116","caller":{"file":"node:internal/timers","fn":"listOnTimeout","id":"85","ix":"-1","pos":"15529","key":"listOnTimeout node:internal/timers"}},{"file":"node:internal/async_hooks","fn":"hasHooks","id":"85","ix":"2","pos":"16116","caller":{"file":"node:internal/timers","fn":"listOnTimeout","id":"85","ix":"-1","pos":"15529","key":"listOnTimeout node:internal/timers"}},{"file":"node:internal/async_hooks","fn":"hasHooks","id":"85","ix":"2","pos":"16116","caller":{"file":"node:internal/timers","fn":"listOnTimeout","id":"85","ix":"-1","pos":"15529","key":"listOnTimeout node:internal/timers"}},{"file":"node:internal/async_hooks","fn":"hasHooks","id":"87","ix":"3","pos":"16116","caller":{"file":"node:internal/timers","fn":"listOnTimeout","id":"87","ix":"-1","pos":"15529","key":"listOnTimeout node:internal/timers"}},{"file":"node:internal/async_hooks","fn":"hasHooks","id":"87","ix":"3","pos":"16116","caller":{"file":"node:internal/timers","fn":"listOnTimeout","id":"87","ix":"-1","pos":"15529","key":"listOnTimeout node:internal/timers"}},{"file":"node:internal/async_hooks","fn":"hasHooks","id":"87","ix":"3","pos":"16116","caller":{"file":"node:internal/timers","fn":"listOnTimeout","id":"87","ix":"-1","pos":"15529","key":"listOnTimeout node:internal/timers"}},{"file":"node:internal/async_hooks","fn":"hasHooks","id":"87","ix":"3","pos":"16116","caller":{"file":"node:internal/timers","fn":"listOnTimeout","id":"87","ix":"-1","pos":"15529","key":"listOnTimeout node:internal/timers"}},{"file":"node:internal/async_hooks","fn":"hasHooks","id":"94","ix":"7","pos":"16116","caller":{"file":"node:_http_server","fn":"resOnFinish","id":"94","ix":"-1","pos":"30286","key":"resOnFinish node:_http_server"}},{"file":"node:internal/async_hooks","fn":"hasHooks","id":"97","ix":"6","pos":"16116","caller":{"file":"node:internal/streams/readable","fn":"emitReadable","id":"97","ix":"-1","pos":"18612","key":"emitReadable node:internal/streams/readable"}}],"getDefaultTriggerAsyncId node:internal/async_hooks":[{"file":"node:internal/async_hooks","fn":"getDefaultTriggerAsyncId","id":"0","ix":"3","pos":"15027","caller":{"file":"node:internal/timers","fn":"initAsyncResource","id":"0","ix":"-1","pos":"5574","key":"initAsyncResource node:internal/timers"}},{"file":"node:internal/async_hooks","fn":"getDefaultTriggerAsyncId","id":"4","ix":"4","pos":"15027","caller":{"file":"node:internal/timers","fn":"Timeout","id":"4","ix":"-1","pos":"5943","key":"Timeout node:internal/timers"}},{"file":"node:internal/async_hooks","fn":"getDefaultTriggerAsyncId","id":"6","ix":"10","pos":"15027","caller":{"file":"file:///home/halister/Documentos/async-se-coda/javascript-expert/modulo12/02-memory-leak/02-leak-events/index.js","fn":"onData","id":"6","ix":"-1","pos":"109","key":"onData file:///home/halister/Documentos/async-se-coda/javascript-expert/modulo12/02-memory-leak/02-leak-events/index.js"}},{"file":"node:internal/async_hooks","fn":"getDefaultTriggerAsyncId","id":"7","ix":"9","pos":"15027","caller":{"file":"node:timers","fn":"setInterval","id":"7","ix":"-1","pos":"5812","key":"setInterval node:timers"}},{"file":"node:internal/async_hooks","fn":"getDefaultTriggerAsyncId","id":"14","ix":"7","pos":"15027","caller":{"file":"node:internal/process/task_queues","fn":"nextTick","id":"14","ix":"-1","pos":"2585","key":"nextTick node:internal/process/task_queues"}},{"file":"node:internal/async_hooks","fn":"getDefaultTriggerAsyncId","id":"22","ix":"9","pos":"15027","caller":{"file":"node:internal/streams/readable","fn":"endReadable","id":"22","ix":"-1","pos":"39631","key":"endReadable node:internal/streams/readable"}},{"file":"node:internal/async_hooks","fn":"getDefaultTriggerAsyncId","id":"27","ix":"10","pos":"15027","caller":{"file":"node:internal/streams/readable","fn":"Readable.resume","id":"27","ix":"-1","pos":"31274","key":"Readable.resume node:internal/streams/readable"}},{"file":"node:internal/async_hooks","fn":"getDefaultTriggerAsyncId","id":"43","ix":"4","pos":"15027","caller":{"file":"node:internal/timers","fn":"Timeout","id":"43","ix":"-1","pos":"5943","key":"Timeout node:internal/timers"}},{"file":"node:internal/async_hooks","fn":"getDefaultTriggerAsyncId","id":"44","ix":"8","pos":"15027","caller":{"file":"node:timers","fn":"setInterval","id":"44","ix":"-1","pos":"5812","key":"setInterval node:timers"}},{"file":"node:internal/async_hooks","fn":"getDefaultTriggerAsyncId","id":"59","ix":"10","pos":"15027","caller":{"file":"node:internal/streams/readable","fn":"Readable.resume","id":"59","ix":"-1","pos":"31274","key":"Readable.resume node:internal/streams/readable"}},{"file":"node:internal/async_hooks","fn":"getDefaultTriggerAsyncId","id":"79","ix":"11","pos":"15027","caller":{"file":"node:net","fn":"Socket.resume","id":"79","ix":"-1","pos":"19778","key":"Socket.resume node:net"}},{"file":"node:internal/async_hooks","fn":"getDefaultTriggerAsyncId","id":"94","ix":"12","pos":"15027","caller":{"file":"node:_http_server","fn":"resOnFinish","id":"94","ix":"-1","pos":"30286","key":"resOnFinish node:_http_server"}},{"file":"node:internal/async_hooks","fn":"getDefaultTriggerAsyncId","id":"97","ix":"9","pos":"15027","caller":{"file":"node:internal/streams/readable","fn":"emitReadable","id":"97","ix":"-1","pos":"18612","key":"emitReadable node:internal/streams/readable"}}],"remove node:internal/linkedlist":[{"file":"node:internal/linkedlist","fn":"remove","id":"2","ix":"0","pos":"275","caller":{"file":"node:internal/linkedlist","fn":"append","id":"2","ix":"-1","pos":"558","key":"append node:internal/linkedlist"}},{"file":"node:internal/linkedlist","fn":"remove","id":"8","ix":"1","pos":"275","caller":{"file":"node:internal/timers","fn":"insert","id":"8","ix":"-1","pos":"10902","key":"insert node:internal/timers"}},{"file":"node:internal/linkedlist","fn":"remove","id":"6","ix":"9","pos":"275","caller":{"file":"file:///home/halister/Documentos/async-se-coda/javascript-expert/modulo12/02-memory-leak/02-leak-events/index.js","fn":"onData","id":"6","ix":"-1","pos":"109","key":"onData file:///home/halister/Documentos/async-se-coda/javascript-expert/modulo12/02-memory-leak/02-leak-events/index.js"}},{"file":"node:internal/linkedlist","fn":"remove","id":"7","ix":"8","pos":"275","caller":{"file":"node:timers","fn":"setInterval","id":"7","ix":"-1","pos":"5812","key":"setInterval node:timers"}},{"file":"node:internal/linkedlist","fn":"remove","id":"33","ix":"0","pos":"275","caller":{"file":"node:internal/linkedlist","fn":"append","id":"33","ix":"-1","pos":"558","key":"append node:internal/linkedlist"}},{"file":"node:internal/linkedlist","fn":"remove","id":"40","ix":"1","pos":"275","caller":{"file":"node:internal/timers","fn":"insert","id":"40","ix":"-1","pos":"10902","key":"insert node:internal/timers"}},{"file":"node:internal/linkedlist","fn":"remove","id":"38","ix":"11","pos":"275","caller":{"file":"node:internal/timers","fn":"listOnTimeout","id":"38","ix":"-1","pos":"15529","key":"listOnTimeout node:internal/timers"}},{"file":"node:internal/linkedlist","fn":"remove","id":"38","ix":"11","pos":"275","caller":{"file":"node:internal/timers","fn":"listOnTimeout","id":"38","ix":"-1","pos":"15529","key":"listOnTimeout node:internal/timers"}},{"file":"node:internal/linkedlist","fn":"remove","id":"44","ix":"10","pos":"275","caller":{"file":"node:timers","fn":"setInterval","id":"44","ix":"-1","pos":"5812","key":"setInterval node:timers"}},{"file":"node:internal/linkedlist","fn":"remove","id":"85","ix":"11","pos":"275","caller":{"file":"node:internal/timers","fn":"listOnTimeout","id":"85","ix":"-1","pos":"15529","key":"listOnTimeout node:internal/timers"}},{"file":"node:internal/linkedlist","fn":"remove","id":"85","ix":"11","pos":"275","caller":{"file":"node:internal/timers","fn":"listOnTimeout","id":"85","ix":"-1","pos":"15529","key":"listOnTimeout node:internal/timers"}},{"file":"node:internal/linkedlist","fn":"remove","id":"87","ix":"6","pos":"275","caller":{"file":"node:internal/timers","fn":"listOnTimeout","id":"87","ix":"-1","pos":"15529","key":"listOnTimeout node:internal/timers"}},{"file":"node:internal/linkedlist","fn":"remove","id":"87","ix":"6","pos":"275","caller":{"file":"node:internal/timers","fn":"listOnTimeout","id":"87","ix":"-1","pos":"15529","key":"listOnTimeout node:internal/timers"}}],"initAsyncResource node:internal/timers":[{"file":"node:internal/timers","fn":"initAsyncResource","id":"4","ix":"0","pos":"5574","caller":{"file":"node:internal/timers","fn":"Timeout","id":"4","ix":"-1","pos":"5943","key":"Timeout node:internal/timers"}},{"file":"node:internal/timers","fn":"initAsyncResource","id":"6","ix":"5","pos":"5574","caller":{"file":"file:///home/halister/Documentos/async-se-coda/javascript-expert/modulo12/02-memory-leak/02-leak-events/index.js","fn":"onData","id":"6","ix":"-1","pos":"109","key":"onData file:///home/halister/Documentos/async-se-coda/javascript-expert/modulo12/02-memory-leak/02-leak-events/index.js"}},{"file":"node:internal/timers","fn":"initAsyncResource","id":"7","ix":"4","pos":"5574","caller":{"file":"node:timers","fn":"setInterval","id":"7","ix":"-1","pos":"5812","key":"setInterval node:timers"}},{"file":"node:internal/timers","fn":"initAsyncResource","id":"43","ix":"0","pos":"5574","caller":{"file":"node:internal/timers","fn":"Timeout","id":"43","ix":"-1","pos":"5943","key":"Timeout node:internal/timers"}},{"file":"node:internal/timers","fn":"initAsyncResource","id":"44","ix":"4","pos":"5574","caller":{"file":"node:timers","fn":"setInterval","id":"44","ix":"-1","pos":"5812","key":"setInterval node:timers"}}],"incRefCount node:internal/timers":[{"file":"node:internal/timers","fn":"incRefCount","id":"4","ix":"5","pos":"9423","caller":{"file":"node:internal/timers","fn":"Timeout","id":"4","ix":"-1","pos":"5943","key":"Timeout node:internal/timers"}},{"file":"node:internal/timers","fn":"incRefCount","id":"7","ix":"10","pos":"9423","caller":{"file":"node:timers","fn":"setInterval","id":"7","ix":"-1","pos":"5812","key":"setInterval node:timers"}},{"file":"node:internal/timers","fn":"incRefCount","id":"43","ix":"5","pos":"9423","caller":{"file":"node:internal/timers","fn":"Timeout","id":"43","ix":"-1","pos":"5943","key":"Timeout node:internal/timers"}},{"file":"node:internal/timers","fn":"incRefCount","id":"44","ix":"9","pos":"9423","caller":{"file":"node:timers","fn":"setInterval","id":"44","ix":"-1","pos":"5812","key":"setInterval node:timers"}}],"append node:internal/linkedlist":[{"file":"node:internal/linkedlist","fn":"append","id":"8","ix":"0","pos":"558","caller":{"file":"node:internal/timers","fn":"insert","id":"8","ix":"-1","pos":"10902","key":"insert node:internal/timers"}},{"file":"node:internal/linkedlist","fn":"append","id":"6","ix":"4","pos":"558","caller":{"file":"file:///home/halister/Documentos/async-se-coda/javascript-expert/modulo12/02-memory-leak/02-leak-events/index.js","fn":"onData","id":"6","ix":"-1","pos":"109","key":"onData file:///home/halister/Documentos/async-se-coda/javascript-expert/modulo12/02-memory-leak/02-leak-events/index.js"}},{"file":"node:internal/linkedlist","fn":"append","id":"7","ix":"3","pos":"558","caller":{"file":"node:timers","fn":"setInterval","id":"7","ix":"-1","pos":"5812","key":"setInterval node:timers"}},{"file":"node:internal/linkedlist","fn":"append","id":"40","ix":"0","pos":"558","caller":{"file":"node:internal/timers","fn":"insert","id":"40","ix":"-1","pos":"10902","key":"insert node:internal/timers"}},{"file":"node:internal/linkedlist","fn":"append","id":"38","ix":"7","pos":"558","caller":{"file":"node:internal/timers","fn":"listOnTimeout","id":"38","ix":"-1","pos":"15529","key":"listOnTimeout node:internal/timers"}},{"file":"node:internal/linkedlist","fn":"append","id":"44","ix":"3","pos":"558","caller":{"file":"node:timers","fn":"setInterval","id":"44","ix":"-1","pos":"5812","key":"setInterval node:timers"}},{"file":"node:internal/linkedlist","fn":"append","id":"85","ix":"8","pos":"558","caller":{"file":"node:internal/timers","fn":"listOnTimeout","id":"85","ix":"-1","pos":"15529","key":"listOnTimeout node:internal/timers"}},{"file":"node:internal/linkedlist","fn":"append","id":"87","ix":"11","pos":"558","caller":{"file":"node:internal/timers","fn":"listOnTimeout","id":"87","ix":"-1","pos":"15529","key":"listOnTimeout node:internal/timers"}}],"setInterval node:timers":[{"file":"node:timers","fn":"setInterval","id":"6","ix":"0","pos":"5812","caller":{"file":"file:///home/halister/Documentos/async-se-coda/javascript-expert/modulo12/02-memory-leak/02-leak-events/index.js","fn":"onData","id":"6","ix":"-1","pos":"109","key":"onData file:///home/halister/Documentos/async-se-coda/javascript-expert/modulo12/02-memory-leak/02-leak-events/index.js"}}],"insert node:internal/timers":[{"file":"node:internal/timers","fn":"insert","id":"6","ix":"1","pos":"10902","caller":{"file":"file:///home/halister/Documentos/async-se-coda/javascript-expert/modulo12/02-memory-leak/02-leak-events/index.js","fn":"onData","id":"6","ix":"-1","pos":"109","key":"onData file:///home/halister/Documentos/async-se-coda/javascript-expert/modulo12/02-memory-leak/02-leak-events/index.js"}},{"file":"node:internal/timers","fn":"insert","id":"7","ix":"0","pos":"10902","caller":{"file":"node:timers","fn":"setInterval","id":"7","ix":"-1","pos":"5812","key":"setInterval node:timers"}},{"file":"node:internal/timers","fn":"insert","id":"38","ix":"5","pos":"10902","caller":{"file":"node:internal/timers","fn":"listOnTimeout","id":"38","ix":"-1","pos":"15529","key":"listOnTimeout node:internal/timers"}},{"file":"node:internal/timers","fn":"insert","id":"44","ix":"0","pos":"10902","caller":{"file":"node:timers","fn":"setInterval","id":"44","ix":"-1","pos":"5812","key":"setInterval node:timers"}},{"file":"node:internal/timers","fn":"insert","id":"85","ix":"7","pos":"10902","caller":{"file":"node:internal/timers","fn":"listOnTimeout","id":"85","ix":"-1","pos":"15529","key":"listOnTimeout node:internal/timers"}},{"file":"node:internal/timers","fn":"insert","id":"87","ix":"7","pos":"10902","caller":{"file":"node:internal/timers","fn":"listOnTimeout","id":"87","ix":"-1","pos":"15529","key":"listOnTimeout node:internal/timers"}}],"Timeout node:internal/timers":[{"file":"node:internal/timers","fn":"Timeout","id":"6","ix":"2","pos":"5943","caller":{"file":"file:///home/halister/Documentos/async-se-coda/javascript-expert/modulo12/02-memory-leak/02-leak-events/index.js","fn":"onData","id":"6","ix":"-1","pos":"109","key":"onData file:///home/halister/Documentos/async-se-coda/javascript-expert/modulo12/02-memory-leak/02-leak-events/index.js"}},{"file":"node:internal/timers","fn":"Timeout","id":"7","ix":"1","pos":"5943","caller":{"file":"node:timers","fn":"setInterval","id":"7","ix":"-1","pos":"5812","key":"setInterval node:timers"}},{"file":"node:internal/timers","fn":"Timeout","id":"44","ix":"1","pos":"5943","caller":{"file":"node:timers","fn":"setInterval","id":"44","ix":"-1","pos":"5812","key":"setInterval node:timers"}}],"enabledHooksExist node:internal/async_hooks":[{"file":"node:internal/async_hooks","fn":"enabledHooksExist","id":"15","ix":"0","pos":"16190","caller":{"file":"node:internal/async_hooks","fn":"popAsyncContext","id":"15","ix":"-1","pos":"18196","key":"popAsyncContext node:internal/async_hooks"}},{"file":"node:internal/async_hooks","fn":"enabledHooksExist","id":"19","ix":"10","pos":"16190","caller":{"file":"node:internal/process/task_queues","fn":"processTicksAndRejections","id":"19","ix":"-1","pos":"1479","key":"processTicksAndRejections node:internal/process/task_queues"}},{"file":"node:internal/async_hooks","fn":"enabledHooksExist","id":"31","ix":"2","pos":"16190","caller":{"file":"node:internal/async_hooks","fn":"emitAfterScript","id":"31","ix":"-1","pos":"17096","key":"emitAfterScript node:internal/async_hooks"}},{"file":"node:internal/async_hooks","fn":"enabledHooksExist","id":"38","ix":"4","pos":"16190","caller":{"file":"node:internal/timers","fn":"listOnTimeout","id":"38","ix":"-1","pos":"15529","key":"listOnTimeout node:internal/timers"}},{"file":"node:internal/async_hooks","fn":"enabledHooksExist","id":"85","ix":"6","pos":"16190","caller":{"file":"node:internal/timers","fn":"listOnTimeout","id":"85","ix":"-1","pos":"15529","key":"listOnTimeout node:internal/timers"}},{"file":"node:internal/async_hooks","fn":"enabledHooksExist","id":"87","ix":"13","pos":"16190","caller":{"file":"node:internal/timers","fn":"listOnTimeout","id":"87","ix":"-1","pos":"15529","key":"listOnTimeout node:internal/timers"}}],"isEmpty node:internal/fixed_queue":[{"file":"node:internal/fixed_queue","fn":"isEmpty","id":"14","ix":"0","pos":"3637","caller":{"file":"node:internal/process/task_queues","fn":"nextTick","id":"14","ix":"-1","pos":"2585","key":"nextTick node:internal/process/task_queues"}},{"file":"node:internal/fixed_queue","fn":"isEmpty","id":"14","ix":"1","pos":"3084","caller":{"file":"node:internal/process/task_queues","fn":"nextTick","id":"14","ix":"-1","pos":"2585","key":"nextTick node:internal/process/task_queues"}},{"file":"node:internal/fixed_queue","fn":"isEmpty","id":"18","ix":"0","pos":"3084","caller":{"file":"node:internal/fixed_queue","fn":"shift","id":"18","ix":"-1","pos":"3954","key":"shift node:internal/fixed_queue"}},{"file":"node:internal/fixed_queue","fn":"isEmpty","id":"19","ix":"2","pos":"3637","caller":{"file":"node:internal/process/task_queues","fn":"processTicksAndRejections","id":"19","ix":"-1","pos":"1479","key":"processTicksAndRejections node:internal/process/task_queues"}},{"file":"node:internal/fixed_queue","fn":"isEmpty","id":"19","ix":"3","pos":"3084","caller":{"file":"node:internal/process/task_queues","fn":"processTicksAndRejections","id":"19","ix":"-1","pos":"1479","key":"processTicksAndRejections node:internal/process/task_queues"}},{"file":"node:internal/fixed_queue","fn":"isEmpty","id":"19","ix":"3","pos":"3084","caller":{"file":"node:internal/process/task_queues","fn":"processTicksAndRejections","id":"19","ix":"-1","pos":"1479","key":"processTicksAndRejections node:internal/process/task_queues"}},{"file":"node:internal/fixed_queue","fn":"isEmpty","id":"22","ix":"2","pos":"3637","caller":{"file":"node:internal/streams/readable","fn":"endReadable","id":"22","ix":"-1","pos":"39631","key":"endReadable node:internal/streams/readable"}},{"file":"node:internal/fixed_queue","fn":"isEmpty","id":"22","ix":"3","pos":"3084","caller":{"file":"node:internal/streams/readable","fn":"endReadable","id":"22","ix":"-1","pos":"39631","key":"endReadable node:internal/streams/readable"}},{"file":"node:internal/fixed_queue","fn":"isEmpty","id":"27","ix":"3","pos":"3637","caller":{"file":"node:internal/streams/readable","fn":"Readable.resume","id":"27","ix":"-1","pos":"31274","key":"Readable.resume node:internal/streams/readable"}},{"file":"node:internal/fixed_queue","fn":"isEmpty","id":"27","ix":"4","pos":"3084","caller":{"file":"node:internal/streams/readable","fn":"Readable.resume","id":"27","ix":"-1","pos":"31274","key":"Readable.resume node:internal/streams/readable"}},{"file":"node:internal/fixed_queue","fn":"isEmpty","id":"59","ix":"3","pos":"3637","caller":{"file":"node:internal/streams/readable","fn":"Readable.resume","id":"59","ix":"-1","pos":"31274","key":"Readable.resume node:internal/streams/readable"}},{"file":"node:internal/fixed_queue","fn":"isEmpty","id":"59","ix":"4","pos":"3084","caller":{"file":"node:internal/streams/readable","fn":"Readable.resume","id":"59","ix":"-1","pos":"31274","key":"Readable.resume node:internal/streams/readable"}},{"file":"node:internal/fixed_queue","fn":"isEmpty","id":"79","ix":"4","pos":"3637","caller":{"file":"node:net","fn":"Socket.resume","id":"79","ix":"-1","pos":"19778","key":"Socket.resume node:net"}},{"file":"node:internal/fixed_queue","fn":"isEmpty","id":"79","ix":"5","pos":"3084","caller":{"file":"node:net","fn":"Socket.resume","id":"79","ix":"-1","pos":"19778","key":"Socket.resume node:net"}},{"file":"node:internal/fixed_queue","fn":"isEmpty","id":"94","ix":"3","pos":"3637","caller":{"file":"node:_http_server","fn":"resOnFinish","id":"94","ix":"-1","pos":"30286","key":"resOnFinish node:_http_server"}},{"file":"node:internal/fixed_queue","fn":"isEmpty","id":"94","ix":"4","pos":"3084","caller":{"file":"node:_http_server","fn":"resOnFinish","id":"94","ix":"-1","pos":"30286","key":"resOnFinish node:_http_server"}},{"file":"node:internal/fixed_queue","fn":"isEmpty","id":"97","ix":"2","pos":"3637","caller":{"file":"node:internal/streams/readable","fn":"emitReadable","id":"97","ix":"-1","pos":"18612","key":"emitReadable node:internal/streams/readable"}},{"file":"node:internal/fixed_queue","fn":"isEmpty","id":"97","ix":"3","pos":"3084","caller":{"file":"node:internal/streams/readable","fn":"emitReadable","id":"97","ix":"-1","pos":"18612","key":"emitReadable node:internal/streams/readable"}}],"push node:internal/fixed_queue":[{"file":"node:internal/fixed_queue","fn":"push","id":"14","ix":"5","pos":"3685","caller":{"file":"node:internal/process/task_queues","fn":"nextTick","id":"14","ix":"-1","pos":"2585","key":"nextTick node:internal/process/task_queues"}},{"file":"node:internal/fixed_queue","fn":"push","id":"14","ix":"9","pos":"3208","caller":{"file":"node:internal/process/task_queues","fn":"nextTick","id":"14","ix":"-1","pos":"2585","key":"nextTick node:internal/process/task_queues"}},{"file":"node:internal/fixed_queue","fn":"push","id":"22","ix":"7","pos":"3685","caller":{"file":"node:internal/streams/readable","fn":"endReadable","id":"22","ix":"-1","pos":"39631","key":"endReadable node:internal/streams/readable"}},{"file":"node:internal/fixed_queue","fn":"push","id":"22","ix":"11","pos":"3208","caller":{"file":"node:internal/streams/readable","fn":"endReadable","id":"22","ix":"-1","pos":"39631","key":"endReadable node:internal/streams/readable"}},{"file":"node:internal/fixed_queue","fn":"push","id":"27","ix":"8","pos":"3685","caller":{"file":"node:internal/streams/readable","fn":"Readable.resume","id":"27","ix":"-1","pos":"31274","key":"Readable.resume node:internal/streams/readable"}},{"file":"node:internal/fixed_queue","fn":"push","id":"27","ix":"12","pos":"3208","caller":{"file":"node:internal/streams/readable","fn":"Readable.resume","id":"27","ix":"-1","pos":"31274","key":"Readable.resume node:internal/streams/readable"}},{"file":"node:internal/fixed_queue","fn":"push","id":"59","ix":"8","pos":"3685","caller":{"file":"node:internal/streams/readable","fn":"Readable.resume","id":"59","ix":"-1","pos":"31274","key":"Readable.resume node:internal/streams/readable"}},{"file":"node:internal/fixed_queue","fn":"push","id":"59","ix":"12","pos":"3208","caller":{"file":"node:internal/streams/readable","fn":"Readable.resume","id":"59","ix":"-1","pos":"31274","key":"Readable.resume node:internal/streams/readable"}},{"file":"node:internal/fixed_queue","fn":"push","id":"79","ix":"9","pos":"3685","caller":{"file":"node:net","fn":"Socket.resume","id":"79","ix":"-1","pos":"19778","key":"Socket.resume node:net"}},{"file":"node:internal/fixed_queue","fn":"push","id":"79","ix":"13","pos":"3208","caller":{"file":"node:net","fn":"Socket.resume","id":"79","ix":"-1","pos":"19778","key":"Socket.resume node:net"}},{"file":"node:internal/fixed_queue","fn":"push","id":"94","ix":"10","pos":"3685","caller":{"file":"node:_http_server","fn":"resOnFinish","id":"94","ix":"-1","pos":"30286","key":"resOnFinish node:_http_server"}},{"file":"node:internal/fixed_queue","fn":"push","id":"94","ix":"14","pos":"3208","caller":{"file":"node:_http_server","fn":"resOnFinish","id":"94","ix":"-1","pos":"30286","key":"resOnFinish node:_http_server"}},{"file":"node:internal/fixed_queue","fn":"push","id":"97","ix":"7","pos":"3685","caller":{"file":"node:internal/streams/readable","fn":"emitReadable","id":"97","ix":"-1","pos":"18612","key":"emitReadable node:internal/streams/readable"}},{"file":"node:internal/fixed_queue","fn":"push","id":"97","ix":"11","pos":"3208","caller":{"file":"node:internal/streams/readable","fn":"emitReadable","id":"97","ix":"-1","pos":"18612","key":"emitReadable node:internal/streams/readable"}}],"isFull node:internal/fixed_queue":[{"file":"node:internal/fixed_queue","fn":"isFull","id":"14","ix":"6","pos":"3139","caller":{"file":"node:internal/process/task_queues","fn":"nextTick","id":"14","ix":"-1","pos":"2585","key":"nextTick node:internal/process/task_queues"}},{"file":"node:internal/fixed_queue","fn":"isFull","id":"22","ix":"8","pos":"3139","caller":{"file":"node:internal/streams/readable","fn":"endReadable","id":"22","ix":"-1","pos":"39631","key":"endReadable node:internal/streams/readable"}},{"file":"node:internal/fixed_queue","fn":"isFull","id":"27","ix":"9","pos":"3139","caller":{"file":"node:internal/streams/readable","fn":"Readable.resume","id":"27","ix":"-1","pos":"31274","key":"Readable.resume node:internal/streams/readable"}},{"file":"node:internal/fixed_queue","fn":"isFull","id":"59","ix":"9","pos":"3139","caller":{"file":"node:internal/streams/readable","fn":"Readable.resume","id":"59","ix":"-1","pos":"31274","key":"Readable.resume node:internal/streams/readable"}},{"file":"node:internal/fixed_queue","fn":"isFull","id":"79","ix":"10","pos":"3139","caller":{"file":"node:net","fn":"Socket.resume","id":"79","ix":"-1","pos":"19778","key":"Socket.resume node:net"}},{"file":"node:internal/fixed_queue","fn":"isFull","id":"94","ix":"11","pos":"3139","caller":{"file":"node:_http_server","fn":"resOnFinish","id":"94","ix":"-1","pos":"30286","key":"resOnFinish node:_http_server"}},{"file":"node:internal/fixed_queue","fn":"isFull","id":"97","ix":"8","pos":"3139","caller":{"file":"node:internal/streams/readable","fn":"emitReadable","id":"97","ix":"-1","pos":"18612","key":"emitReadable node:internal/streams/readable"}}],"pushAsyncContext node:internal/async_hooks":[{"file":"node:internal/async_hooks","fn":"pushAsyncContext","id":"17","ix":"1","pos":"17562","caller":{"file":"node:internal/async_hooks","fn":"emitBeforeScript","id":"17","ix":"-1","pos":"16918","key":"emitBeforeScript node:internal/async_hooks"}},{"file":"node:internal/async_hooks","fn":"pushAsyncContext","id":"19","ix":"12","pos":"17562","caller":{"file":"node:internal/process/task_queues","fn":"processTicksAndRejections","id":"19","ix":"-1","pos":"1479","key":"processTicksAndRejections node:internal/process/task_queues"}},{"file":"node:internal/async_hooks","fn":"pushAsyncContext","id":"38","ix":"10","pos":"17562","caller":{"file":"node:internal/timers","fn":"listOnTimeout","id":"38","ix":"-1","pos":"15529","key":"listOnTimeout node:internal/timers"}},{"file":"node:internal/async_hooks","fn":"pushAsyncContext","id":"85","ix":"10","pos":"17562","caller":{"file":"node:internal/timers","fn":"listOnTimeout","id":"85","ix":"-1","pos":"15529","key":"listOnTimeout node:internal/timers"}}],"shift node:internal/fixed_queue":[{"file":"node:internal/fixed_queue","fn":"shift","id":"18","ix":"1","pos":"3300","caller":{"file":"node:internal/fixed_queue","fn":"shift","id":"18","ix":"-1","pos":"3954","key":"shift node:internal/fixed_queue"}},{"file":"node:internal/fixed_queue","fn":"shift","id":"19","ix":"6","pos":"3954","caller":{"file":"node:internal/process/task_queues","fn":"processTicksAndRejections","id":"19","ix":"-1","pos":"1479","key":"processTicksAndRejections node:internal/process/task_queues"}},{"file":"node:internal/fixed_queue","fn":"shift","id":"19","ix":"7","pos":"3300","caller":{"file":"node:internal/process/task_queues","fn":"processTicksAndRejections","id":"19","ix":"-1","pos":"1479","key":"processTicksAndRejections node:internal/process/task_queues"}}],"destroyHooksExist node:internal/async_hooks":[{"file":"node:internal/async_hooks","fn":"destroyHooksExist","id":"19","ix":"0","pos":"16367","caller":{"file":"node:internal/process/task_queues","fn":"processTicksAndRejections","id":"19","ix":"-1","pos":"1479","key":"processTicksAndRejections node:internal/process/task_queues"}},{"file":"node:internal/async_hooks","fn":"destroyHooksExist","id":"85","ix":"1","pos":"16367","caller":{"file":"node:internal/timers","fn":"listOnTimeout","id":"85","ix":"-1","pos":"15529","key":"listOnTimeout node:internal/timers"}},{"file":"node:internal/async_hooks","fn":"destroyHooksExist","id":"87","ix":"2","pos":"16367","caller":{"file":"node:internal/timers","fn":"listOnTimeout","id":"87","ix":"-1","pos":"15529","key":"listOnTimeout node:internal/timers"}}],"setHasTickScheduled node:internal/process/task_queues":[{"file":"node:internal/process/task_queues","fn":"setHasTickScheduled","id":"19","ix":"4","pos":"1087","caller":{"file":"node:internal/process/task_queues","fn":"processTicksAndRejections","id":"19","ix":"-1","pos":"1479","key":"processTicksAndRejections node:internal/process/task_queues"}}],"setHasRejectionToWarn node:internal/process/promises":[{"file":"node:internal/process/promises","fn":"setHasRejectionToWarn","id":"19","ix":"5","pos":"2185","caller":{"file":"node:internal/process/task_queues","fn":"processTicksAndRejections","id":"19","ix":"-1","pos":"1479","key":"processTicksAndRejections node:internal/process/task_queues"}}],"emitAfterScript node:internal/async_hooks":[{"file":"node:internal/async_hooks","fn":"emitAfterScript","id":"19","ix":"8","pos":"17096","caller":{"file":"node:internal/process/task_queues","fn":"processTicksAndRejections","id":"19","ix":"-1","pos":"1479","key":"processTicksAndRejections node:internal/process/task_queues"}},{"file":"node:internal/async_hooks","fn":"emitAfterScript","id":"38","ix":"1","pos":"17096","caller":{"file":"node:internal/timers","fn":"listOnTimeout","id":"38","ix":"-1","pos":"15529","key":"listOnTimeout node:internal/timers"}},{"file":"node:internal/async_hooks","fn":"emitAfterScript","id":"85","ix":"4","pos":"17096","caller":{"file":"node:internal/timers","fn":"listOnTimeout","id":"85","ix":"-1","pos":"15529","key":"listOnTimeout node:internal/timers"}},{"file":"node:internal/async_hooks","fn":"emitAfterScript","id":"87","ix":"4","pos":"17096","caller":{"file":"node:internal/timers","fn":"listOnTimeout","id":"87","ix":"-1","pos":"15529","key":"listOnTimeout node:internal/timers"}}],"popAsyncContext node:internal/async_hooks":[{"file":"node:internal/async_hooks","fn":"popAsyncContext","id":"19","ix":"9","pos":"18196","caller":{"file":"node:internal/process/task_queues","fn":"processTicksAndRejections","id":"19","ix":"-1","pos":"1479","key":"processTicksAndRejections node:internal/process/task_queues"}},{"file":"node:internal/async_hooks","fn":"popAsyncContext","id":"31","ix":"1","pos":"18196","caller":{"file":"node:internal/async_hooks","fn":"emitAfterScript","id":"31","ix":"-1","pos":"17096","key":"emitAfterScript node:internal/async_hooks"}},{"file":"node:internal/async_hooks","fn":"popAsyncContext","id":"38","ix":"3","pos":"18196","caller":{"file":"node:internal/timers","fn":"listOnTimeout","id":"38","ix":"-1","pos":"15529","key":"listOnTimeout node:internal/timers"}},{"file":"node:internal/async_hooks","fn":"popAsyncContext","id":"85","ix":"5","pos":"18196","caller":{"file":"node:internal/timers","fn":"listOnTimeout","id":"85","ix":"-1","pos":"15529","key":"listOnTimeout node:internal/timers"}},{"file":"node:internal/async_hooks","fn":"popAsyncContext","id":"87","ix":"12","pos":"18196","caller":{"file":"node:internal/timers","fn":"listOnTimeout","id":"87","ix":"-1","pos":"15529","key":"listOnTimeout node:internal/timers"}}],"emitBeforeScript node:internal/async_hooks":[{"file":"node:internal/async_hooks","fn":"emitBeforeScript","id":"19","ix":"11","pos":"16918","caller":{"file":"node:internal/process/task_queues","fn":"processTicksAndRejections","id":"19","ix":"-1","pos":"1479","key":"processTicksAndRejections node:internal/process/task_queues"}},{"file":"node:internal/async_hooks","fn":"emitBeforeScript","id":"38","ix":"9","pos":"16918","caller":{"file":"node:internal/timers","fn":"listOnTimeout","id":"38","ix":"-1","pos":"15529","key":"listOnTimeout node:internal/timers"}},{"file":"node:internal/async_hooks","fn":"emitBeforeScript","id":"85","ix":"9","pos":"16918","caller":{"file":"node:internal/timers","fn":"listOnTimeout","id":"85","ix":"-1","pos":"15529","key":"listOnTimeout node:internal/timers"}},{"file":"node:internal/async_hooks","fn":"emitBeforeScript","id":"87","ix":"5","pos":"16918","caller":{"file":"node:internal/timers","fn":"listOnTimeout","id":"87","ix":"-1","pos":"15529","key":"listOnTimeout node:internal/timers"}}],"onError node:_http_incoming":[{"file":"node:_http_incoming","fn":"onError","id":"19","ix":"13","pos":"14604","caller":{"file":"node:internal/process/task_queues","fn":"processTicksAndRejections","id":"19","ix":"-1","pos":"1479","key":"processTicksAndRejections node:internal/process/task_queues"}}],"onDestroy node:internal/streams/destroy":[{"file":"node:internal/streams/destroy","fn":"onDestroy","id":"19","ix":"14","pos":"1648","caller":{"file":"node:internal/process/task_queues","fn":"processTicksAndRejections","id":"19","ix":"-1","pos":"1479","key":"processTicksAndRejections node:internal/process/task_queues"}}],"noop node:internal/util/debuglog":[{"file":"node:internal/util/debuglog","fn":"noop","id":"22","ix":"0","pos":"1404","caller":{"file":"node:internal/streams/readable","fn":"endReadable","id":"22","ix":"-1","pos":"39631","key":"endReadable node:internal/streams/readable"}},{"file":"node:internal/util/debuglog","fn":"noop","id":"27","ix":"0","pos":"1404","caller":{"file":"node:internal/streams/readable","fn":"Readable.resume","id":"27","ix":"-1","pos":"31274","key":"Readable.resume node:internal/streams/readable"}},{"file":"node:internal/util/debuglog","fn":"noop","id":"28","ix":"0","pos":"1404","caller":{"file":"node:internal/streams/readable","fn":"flow","id":"28","ix":"-1","pos":"32309","key":"flow node:internal/streams/readable"}},{"file":"node:internal/util/debuglog","fn":"noop","id":"38","ix":"6","pos":"1404","caller":{"file":"node:internal/timers","fn":"listOnTimeout","id":"38","ix":"-1","pos":"15529","key":"listOnTimeout node:internal/timers"}},{"file":"node:internal/util/debuglog","fn":"noop","id":"56","ix":"0","pos":"1404","caller":{"file":"node:internal/streams/readable","fn":"Readable.read","id":"56","ix":"-1","pos":"13087","key":"Readable.read node:internal/streams/readable"}},{"file":"node:internal/util/debuglog","fn":"noop","id":"59","ix":"0","pos":"1404","caller":{"file":"node:internal/streams/readable","fn":"Readable.resume","id":"59","ix":"-1","pos":"31274","key":"Readable.resume node:internal/streams/readable"}},{"file":"node:internal/util/debuglog","fn":"noop","id":"62","ix":"0","pos":"1404","caller":{"file":"node:internal/streams/readable","fn":"endReadableNT","id":"62","ix":"-1","pos":"39856","key":"endReadableNT node:internal/streams/readable"}},{"file":"node:internal/util/debuglog","fn":"noop","id":"79","ix":"1","pos":"1404","caller":{"file":"node:net","fn":"Socket.resume","id":"79","ix":"-1","pos":"19778","key":"Socket.resume node:net"}},{"file":"node:internal/util/debuglog","fn":"noop","id":"81","ix":"1","pos":"1404","caller":{"file":"node:_http_incoming","fn":"_dump","id":"81","ix":"-1","pos":"14358","key":"_dump node:_http_incoming"}},{"file":"node:internal/util/debuglog","fn":"noop","id":"82","ix":"0","pos":"1404","caller":{"file":"node:internal/streams/readable","fn":"emitReadable_","id":"82","ix":"-1","pos":"18942","key":"emitReadable_ node:internal/streams/readable"}},{"file":"node:internal/util/debuglog","fn":"noop","id":"82","ix":"0","pos":"1404","caller":{"file":"node:internal/streams/readable","fn":"emitReadable_","id":"82","ix":"-1","pos":"18942","key":"emitReadable_ node:internal/streams/readable"}},{"file":"node:internal/util/debuglog","fn":"noop","id":"85","ix":"3","pos":"1404","caller":{"file":"node:internal/timers","fn":"listOnTimeout","id":"85","ix":"-1","pos":"15529","key":"listOnTimeout node:internal/timers"}},{"file":"node:internal/util/debuglog","fn":"noop","id":"85","ix":"3","pos":"1404","caller":{"file":"node:internal/timers","fn":"listOnTimeout","id":"85","ix":"-1","pos":"15529","key":"listOnTimeout node:internal/timers"}},{"file":"node:internal/util/debuglog","fn":"noop","id":"85","ix":"3","pos":"1404","caller":{"file":"node:internal/timers","fn":"listOnTimeout","id":"85","ix":"-1","pos":"15529","key":"listOnTimeout node:internal/timers"}},{"file":"node:internal/util/debuglog","fn":"noop","id":"87","ix":"0","pos":"1404","caller":{"file":"node:internal/timers","fn":"listOnTimeout","id":"87","ix":"-1","pos":"15529","key":"listOnTimeout node:internal/timers"}},{"file":"node:internal/util/debuglog","fn":"noop","id":"87","ix":"0","pos":"1404","caller":{"file":"node:internal/timers","fn":"listOnTimeout","id":"87","ix":"-1","pos":"15529","key":"listOnTimeout node:internal/timers"}},{"file":"node:internal/util/debuglog","fn":"noop","id":"87","ix":"0","pos":"1404","caller":{"file":"node:internal/timers","fn":"listOnTimeout","id":"87","ix":"-1","pos":"15529","key":"listOnTimeout node:internal/timers"}},{"file":"node:internal/util/debuglog","fn":"noop","id":"87","ix":"0","pos":"1404","caller":{"file":"node:internal/timers","fn":"listOnTimeout","id":"87","ix":"-1","pos":"15529","key":"listOnTimeout node:internal/timers"}},{"file":"node:internal/util/debuglog","fn":"noop","id":"93","ix":"0","pos":"1404","caller":{"file":"node:internal/streams/readable","fn":"resume_","id":"93","ix":"-1","pos":"31762","key":"resume_ node:internal/streams/readable"}},{"file":"node:internal/util/debuglog","fn":"noop","id":"93","ix":"0","pos":"1404","caller":{"file":"node:internal/streams/readable","fn":"resume_","id":"93","ix":"-1","pos":"31762","key":"resume_ node:internal/streams/readable"}},{"file":"node:internal/util/debuglog","fn":"noop","id":"97","ix":"0","pos":"1404","caller":{"file":"node:internal/streams/readable","fn":"emitReadable","id":"97","ix":"-1","pos":"18612","key":"emitReadable node:internal/streams/readable"}},{"file":"node:internal/util/debuglog","fn":"noop","id":"97","ix":"0","pos":"1404","caller":{"file":"node:internal/streams/readable","fn":"emitReadable","id":"97","ix":"-1","pos":"18612","key":"emitReadable node:internal/streams/readable"}},{"file":"node:internal/util/debuglog","fn":"noop","id":"101","ix":"2","pos":"1404","caller":{"file":"node:_http_outgoing","fn":"end","id":"101","ix":"-1","pos":"29396","key":"end node:_http_outgoing"}},{"file":"node:internal/util/debuglog","fn":"noop","id":"102","ix":"1","pos":"1404","caller":{"file":"node:_http_outgoing","fn":"write_","id":"102","ix":"-1","pos":"25617","key":"write_ node:_http_outgoing"}}],"nextTick node:internal/process/task_queues":[{"file":"node:internal/process/task_queues","fn":"nextTick","id":"22","ix":"1","pos":"2585","caller":{"file":"node:internal/streams/readable","fn":"endReadable","id":"22","ix":"-1","pos":"39631","key":"endReadable node:internal/streams/readable"}},{"file":"node:internal/process/task_queues","fn":"nextTick","id":"27","ix":"2","pos":"2585","caller":{"file":"node:internal/streams/readable","fn":"Readable.resume","id":"27","ix":"-1","pos":"31274","key":"Readable.resume node:internal/streams/readable"}},{"file":"node:internal/process/task_queues","fn":"nextTick","id":"59","ix":"2","pos":"2585","caller":{"file":"node:internal/streams/readable","fn":"Readable.resume","id":"59","ix":"-1","pos":"31274","key":"Readable.resume node:internal/streams/readable"}},{"file":"node:internal/process/task_queues","fn":"nextTick","id":"79","ix":"3","pos":"2585","caller":{"file":"node:net","fn":"Socket.resume","id":"79","ix":"-1","pos":"19778","key":"Socket.resume node:net"}},{"file":"node:internal/process/task_queues","fn":"nextTick","id":"94","ix":"2","pos":"2585","caller":{"file":"node:_http_server","fn":"resOnFinish","id":"94","ix":"-1","pos":"30286","key":"resOnFinish node:_http_server"}},{"file":"node:internal/process/task_queues","fn":"nextTick","id":"97","ix":"1","pos":"2585","caller":{"file":"node:internal/streams/readable","fn":"emitReadable","id":"97","ix":"-1","pos":"18612","key":"emitReadable node:internal/streams/readable"}}],"_addListener node:events":[{"file":"node:events","fn":"_addListener","id":"26","ix":"0","pos":"15486","caller":{"file":"node:events","fn":"addListener","id":"26","ix":"-1","pos":"17557","key":"addListener node:events"}},{"file":"node:events","fn":"_addListener","id":"53","ix":"0","pos":"15486","caller":{"file":"node:events","fn":"addListener","id":"53","ix":"-1","pos":"17557","key":"addListener node:events"}}],"checkListener node:events":[{"file":"node:events","fn":"checkListener","id":"26","ix":"1","pos":"7910","caller":{"file":"node:events","fn":"addListener","id":"26","ix":"-1","pos":"17557","key":"addListener node:events"}},{"file":"node:events","fn":"checkListener","id":"53","ix":"3","pos":"7910","caller":{"file":"node:events","fn":"addListener","id":"53","ix":"-1","pos":"17557","key":"addListener node:events"}},{"file":"node:events","fn":"checkListener","id":"68","ix":"4","pos":"7910","caller":{"file":"node:_http_server","fn":"detachSocket","id":"68","ix":"-1","pos":"10209","key":"detachSocket node:_http_server"}}],"_getMaxListeners node:events":[{"file":"node:events","fn":"_getMaxListeners","id":"26","ix":"2","pos":"11878","caller":{"file":"node:events","fn":"addListener","id":"26","ix":"-1","pos":"17557","key":"addListener node:events"}},{"file":"node:events","fn":"_getMaxListeners","id":"53","ix":"1","pos":"11878","caller":{"file":"node:events","fn":"addListener","id":"53","ix":"-1","pos":"17557","key":"addListener node:events"}}],"get node:events":[{"file":"node:events","fn":"get","id":"26","ix":"3","pos":"8082","caller":{"file":"node:events","fn":"addListener","id":"26","ix":"-1","pos":"17557","key":"addListener node:events"}},{"file":"node:events","fn":"get","id":"53","ix":"2","pos":"8082","caller":{"file":"node:events","fn":"addListener","id":"53","ix":"-1","pos":"17557","key":"addListener node:events"}}],"resume node:internal/streams/readable":[{"file":"node:internal/streams/readable","fn":"resume","id":"27","ix":"1","pos":"31609","caller":{"file":"node:internal/streams/readable","fn":"Readable.resume","id":"27","ix":"-1","pos":"31274","key":"Readable.resume node:internal/streams/readable"}},{"file":"node:internal/streams/readable","fn":"resume","id":"59","ix":"1","pos":"31609","caller":{"file":"node:internal/streams/readable","fn":"Readable.resume","id":"59","ix":"-1","pos":"31274","key":"Readable.resume node:internal/streams/readable"}},{"file":"node:internal/streams/readable","fn":"resume","id":"79","ix":"2","pos":"31609","caller":{"file":"node:net","fn":"Socket.resume","id":"79","ix":"-1","pos":"19778","key":"Socket.resume node:net"}},{"file":"node:internal/streams/readable","fn":"resume","id":"81","ix":"4","pos":"31609","caller":{"file":"node:_http_incoming","fn":"_dump","id":"81","ix":"-1","pos":"14358","key":"_dump node:_http_incoming"}}],"Socket.read node:net":[{"file":"node:net","fn":"Socket.read","id":"28","ix":"1","pos":"19990","caller":{"file":"node:internal/streams/readable","fn":"flow","id":"28","ix":"-1","pos":"32309","key":"flow node:internal/streams/readable"}},{"file":"node:net","fn":"Socket.read","id":"82","ix":"4","pos":"19990","caller":{"file":"node:internal/streams/readable","fn":"emitReadable_","id":"82","ix":"-1","pos":"18942","key":"emitReadable_ node:internal/streams/readable"}},{"file":"node:net","fn":"Socket.read","id":"93","ix":"4","pos":"19990","caller":{"file":"node:internal/streams/readable","fn":"resume_","id":"93","ix":"-1","pos":"31762","key":"resume_ node:internal/streams/readable"}}],"emit node:events":[{"file":"node:events","fn":"emit","id":"29","ix":"0","pos":"13172","caller":{"file":"file:///home/halister/Documentos/async-se-coda/javascript-expert/modulo12/02-memory-leak/02-leak-events/index.js","fn":"handler","id":"29","ix":"-1","pos":"233","key":"handler file:///home/halister/Documentos/async-se-coda/javascript-expert/modulo12/02-memory-leak/02-leak-events/index.js"}},{"file":"node:events","fn":"emit","id":"30","ix":"2","pos":"13172","caller":{"file":"node:_http_server","fn":"assignSocket","id":"30","ix":"-1","pos":"9954","key":"assignSocket node:_http_server"}},{"file":"node:events","fn":"emit","id":"52","ix":"0","pos":"13172","caller":{"file":"node:internal/streams/destroy","fn":"emitCloseNT","id":"52","ix":"-1","pos":"2295","key":"emitCloseNT node:internal/streams/destroy"}},{"file":"node:events","fn":"emit","id":"62","ix":"2","pos":"13172","caller":{"file":"node:internal/streams/readable","fn":"endReadableNT","id":"62","ix":"-1","pos":"39856","key":"endReadableNT node:internal/streams/readable"}},{"file":"node:events","fn":"emit","id":"67","ix":"2","pos":"13172","caller":{"file":"node:_http_server","fn":"assignSocket","id":"67","ix":"-1","pos":"9954","key":"assignSocket node:_http_server"}},{"file":"node:events","fn":"emit","id":"80","ix":"0","pos":"13172","caller":{"file":"node:_http_outgoing","fn":"onFinish","id":"80","ix":"-1","pos":"29247","key":"onFinish node:_http_outgoing"}},{"file":"node:events","fn":"emit","id":"82","ix":"2","pos":"13172","caller":{"file":"node:internal/streams/readable","fn":"emitReadable_","id":"82","ix":"-1","pos":"18942","key":"emitReadable_ node:internal/streams/readable"}},{"file":"node:events","fn":"emit","id":"89","ix":"0","pos":"13172","caller":{"file":"node:_http_server","fn":"emitCloseNT","id":"89","ix":"-1","pos":"31612","key":"emitCloseNT node:_http_server"}},{"file":"node:events","fn":"emit","id":"91","ix":"2","pos":"13172","caller":{"file":"node:_http_server","fn":"parserOnIncoming","id":"91","ix":"-1","pos":"31916","key":"parserOnIncoming node:_http_server"}},{"file":"node:events","fn":"emit","id":"93","ix":"2","pos":"13172","caller":{"file":"node:internal/streams/readable","fn":"resume_","id":"93","ix":"-1","pos":"31762","key":"resume_ node:internal/streams/readable"}},{"file":"node:events","fn":"emit","id":"95","ix":"1","pos":"13172","caller":{"file":"node:_http_outgoing","fn":"_finish","id":"95","ix":"-1","pos":"31536","key":"_finish node:_http_outgoing"}}],"onData file:///home/halister/Documentos/async-se-coda/javascript-expert/modulo12/02-memory-leak/02-leak-events/index.js":[{"file":"file:///home/halister/Documentos/async-se-coda/javascript-expert/modulo12/02-memory-leak/02-leak-events/index.js","fn":"onData","id":"29","ix":"1","pos":"109","caller":{"file":"file:///home/halister/Documentos/async-se-coda/javascript-expert/modulo12/02-memory-leak/02-leak-events/index.js","fn":"handler","id":"29","ix":"-1","pos":"233","key":"handler file:///home/halister/Documentos/async-se-coda/javascript-expert/modulo12/02-memory-leak/02-leak-events/index.js"}},{"file":"file:///home/halister/Documentos/async-se-coda/javascript-expert/modulo12/02-memory-leak/02-leak-events/index.js","fn":"onData","id":"30","ix":"3","pos":"109","caller":{"file":"node:_http_server","fn":"assignSocket","id":"30","ix":"-1","pos":"9954","key":"assignSocket node:_http_server"}},{"file":"file:///home/halister/Documentos/async-se-coda/javascript-expert/modulo12/02-memory-leak/02-leak-events/index.js","fn":"onData","id":"52","ix":"1","pos":"109","caller":{"file":"node:internal/streams/destroy","fn":"emitCloseNT","id":"52","ix":"-1","pos":"2295","key":"emitCloseNT node:internal/streams/destroy"}},{"file":"file:///home/halister/Documentos/async-se-coda/javascript-expert/modulo12/02-memory-leak/02-leak-events/index.js","fn":"onData","id":"62","ix":"3","pos":"109","caller":{"file":"node:internal/streams/readable","fn":"endReadableNT","id":"62","ix":"-1","pos":"39856","key":"endReadableNT node:internal/streams/readable"}},{"file":"file:///home/halister/Documentos/async-se-coda/javascript-expert/modulo12/02-memory-leak/02-leak-events/index.js","fn":"onData","id":"67","ix":"3","pos":"109","caller":{"file":"node:_http_server","fn":"assignSocket","id":"67","ix":"-1","pos":"9954","key":"assignSocket node:_http_server"}},{"file":"file:///home/halister/Documentos/async-se-coda/javascript-expert/modulo12/02-memory-leak/02-leak-events/index.js","fn":"onData","id":"80","ix":"1","pos":"109","caller":{"file":"node:_http_outgoing","fn":"onFinish","id":"80","ix":"-1","pos":"29247","key":"onFinish node:_http_outgoing"}},{"file":"file:///home/halister/Documentos/async-se-coda/javascript-expert/modulo12/02-memory-leak/02-leak-events/index.js","fn":"onData","id":"82","ix":"3","pos":"109","caller":{"file":"node:internal/streams/readable","fn":"emitReadable_","id":"82","ix":"-1","pos":"18942","key":"emitReadable_ node:internal/streams/readable"}},{"file":"file:///home/halister/Documentos/async-se-coda/javascript-expert/modulo12/02-memory-leak/02-leak-events/index.js","fn":"onData","id":"89","ix":"1","pos":"109","caller":{"file":"node:_http_server","fn":"emitCloseNT","id":"89","ix":"-1","pos":"31612","key":"emitCloseNT node:_http_server"}},{"file":"file:///home/halister/Documentos/async-se-coda/javascript-expert/modulo12/02-memory-leak/02-leak-events/index.js","fn":"onData","id":"91","ix":"3","pos":"109","caller":{"file":"node:_http_server","fn":"parserOnIncoming","id":"91","ix":"-1","pos":"31916","key":"parserOnIncoming node:_http_server"}},{"file":"file:///home/halister/Documentos/async-se-coda/javascript-expert/modulo12/02-memory-leak/02-leak-events/index.js","fn":"onData","id":"93","ix":"3","pos":"109","caller":{"file":"node:internal/streams/readable","fn":"resume_","id":"93","ix":"-1","pos":"31762","key":"resume_ node:internal/streams/readable"}},{"file":"file:///home/halister/Documentos/async-se-coda/javascript-expert/modulo12/02-memory-leak/02-leak-events/index.js","fn":"onData","id":"95","ix":"2","pos":"109","caller":{"file":"node:_http_outgoing","fn":"_finish","id":"95","ix":"-1","pos":"31536","key":"_finish node:_http_outgoing"}}],"assert node:internal/assert":[{"file":"node:internal/assert","fn":"assert","id":"30","ix":"0","pos":"172","caller":{"file":"node:_http_server","fn":"assignSocket","id":"30","ix":"-1","pos":"9954","key":"assignSocket node:_http_server"}},{"file":"node:internal/assert","fn":"assert","id":"68","ix":"0","pos":"172","caller":{"file":"node:_http_server","fn":"detachSocket","id":"68","ix":"-1","pos":"10209","key":"detachSocket node:_http_server"}},{"file":"node:internal/assert","fn":"assert","id":"67","ix":"0","pos":"172","caller":{"file":"node:_http_server","fn":"assignSocket","id":"67","ix":"-1","pos":"9954","key":"assignSocket node:_http_server"}},{"file":"node:internal/assert","fn":"assert","id":"94","ix":"1","pos":"172","caller":{"file":"node:_http_server","fn":"resOnFinish","id":"94","ix":"-1","pos":"30286","key":"resOnFinish node:_http_server"}},{"file":"node:internal/assert","fn":"assert","id":"95","ix":"0","pos":"172","caller":{"file":"node:_http_outgoing","fn":"_finish","id":"95","ix":"-1","pos":"31536","key":"_finish node:_http_outgoing"}}],"_flush node:_http_outgoing":[{"file":"node:_http_outgoing","fn":"_flush","id":"30","ix":"1","pos":"32400","caller":{"file":"node:_http_server","fn":"assignSocket","id":"30","ix":"-1","pos":"9954","key":"assignSocket node:_http_server"}},{"file":"node:_http_outgoing","fn":"_flush","id":"67","ix":"1","pos":"32400","caller":{"file":"node:_http_server","fn":"assignSocket","id":"67","ix":"-1","pos":"9954","key":"assignSocket node:_http_server"}}],"socketListenerWrap node:_http_server":[{"file":"node:_http_server","fn":"socketListenerWrap","id":"30","ix":"4","pos":"36530","caller":{"file":"node:_http_server","fn":"assignSocket","id":"30","ix":"-1","pos":"9954","key":"assignSocket node:_http_server"}},{"file":"node:_http_server","fn":"socketListenerWrap","id":"67","ix":"4","pos":"36530","caller":{"file":"node:_http_server","fn":"assignSocket","id":"67","ix":"-1","pos":"9954","key":"assignSocket node:_http_server"}}],"_flushOutput node:_http_outgoing":[{"file":"node:_http_outgoing","fn":"_flushOutput","id":"30","ix":"5","pos":"32880","caller":{"file":"node:_http_server","fn":"assignSocket","id":"30","ix":"-1","pos":"9954","key":"assignSocket node:_http_server"}}],"Writable.cork node:internal/streams/writable":[{"file":"node:internal/streams/writable","fn":"Writable.cork","id":"30","ix":"6","pos":"11096","caller":{"file":"node:_http_server","fn":"assignSocket","id":"30","ix":"-1","pos":"9954","key":"assignSocket node:_http_server"}},{"file":"node:internal/streams/writable","fn":"Writable.cork","id":"88","ix":"0","pos":"11096","caller":{"file":"node:_http_outgoing","fn":"_flushOutput","id":"88","ix":"-1","pos":"32880","key":"_flushOutput node:_http_outgoing"}}],"Writable.write node:internal/streams/writable":[{"file":"node:internal/streams/writable","fn":"Writable.write","id":"30","ix":"7","pos":"10981","caller":{"file":"node:_http_server","fn":"assignSocket","id":"30","ix":"-1","pos":"9954","key":"assignSocket node:_http_server"}},{"file":"node:internal/streams/writable","fn":"Writable.write","id":"88","ix":"1","pos":"10981","caller":{"file":"node:_http_outgoing","fn":"_flushOutput","id":"88","ix":"-1","pos":"32880","key":"_flushOutput node:_http_outgoing"}}],"hasTickScheduled node:internal/process/task_queues":[{"file":"node:internal/process/task_queues","fn":"hasTickScheduled","id":"34","ix":"0","pos":"1007","caller":{"file":"node:internal/process/task_queues","fn":"runNextTicks","id":"34","ix":"-1","pos":"1268","key":"runNextTicks node:internal/process/task_queues"}},{"file":"node:internal/process/task_queues","fn":"hasTickScheduled","id":"34","ix":"0","pos":"1007","caller":{"file":"node:internal/process/task_queues","fn":"runNextTicks","id":"34","ix":"-1","pos":"1268","key":"runNextTicks node:internal/process/task_queues"}},{"file":"node:internal/process/task_queues","fn":"hasTickScheduled","id":"87","ix":"9","pos":"1007","caller":{"file":"node:internal/timers","fn":"listOnTimeout","id":"87","ix":"-1","pos":"15529","key":"listOnTimeout node:internal/timers"}},{"file":"node:internal/process/task_queues","fn":"hasTickScheduled","id":"87","ix":"9","pos":"1007","caller":{"file":"node:internal/timers","fn":"listOnTimeout","id":"87","ix":"-1","pos":"15529","key":"listOnTimeout node:internal/timers"}}],"hasRejectionToWarn node:internal/process/promises":[{"file":"node:internal/process/promises","fn":"hasRejectionToWarn","id":"34","ix":"1","pos":"2274","caller":{"file":"node:internal/process/task_queues","fn":"runNextTicks","id":"34","ix":"-1","pos":"1268","key":"runNextTicks node:internal/process/task_queues"}},{"file":"node:internal/process/promises","fn":"hasRejectionToWarn","id":"34","ix":"1","pos":"2274","caller":{"file":"node:internal/process/task_queues","fn":"runNextTicks","id":"34","ix":"-1","pos":"1268","key":"runNextTicks node:internal/process/task_queues"}},{"file":"node:internal/process/promises","fn":"hasRejectionToWarn","id":"87","ix":"10","pos":"2274","caller":{"file":"node:internal/timers","fn":"listOnTimeout","id":"87","ix":"-1","pos":"15529","key":"listOnTimeout node:internal/timers"}},{"file":"node:internal/process/promises","fn":"hasRejectionToWarn","id":"87","ix":"10","pos":"2274","caller":{"file":"node:internal/timers","fn":"listOnTimeout","id":"87","ix":"-1","pos":"15529","key":"listOnTimeout node:internal/timers"}}],"peek node:internal/linkedlist":[{"file":"node:internal/linkedlist","fn":"peek","id":"38","ix":"0","pos":"146","caller":{"file":"node:internal/timers","fn":"listOnTimeout","id":"38","ix":"-1","pos":"15529","key":"listOnTimeout node:internal/timers"}},{"file":"node:internal/linkedlist","fn":"peek","id":"85","ix":"0","pos":"146","caller":{"file":"node:internal/timers","fn":"listOnTimeout","id":"85","ix":"-1","pos":"15529","key":"listOnTimeout node:internal/timers"}},{"file":"node:internal/linkedlist","fn":"peek","id":"87","ix":"1","pos":"146","caller":{"file":"node:internal/timers","fn":"listOnTimeout","id":"87","ix":"-1","pos":"15529","key":"listOnTimeout node:internal/timers"}}],"myInterval file:///home/halister/Documentos/async-se-coda/javascript-expert/modulo12/02-memory-leak/02-leak-events/index.js":[{"file":"file:///home/halister/Documentos/async-se-coda/javascript-expert/modulo12/02-memory-leak/02-leak-events/index.js","fn":"myInterval","id":"38","ix":"8","pos":"170","caller":{"file":"node:internal/timers","fn":"listOnTimeout","id":"38","ix":"-1","pos":"15529","key":"listOnTimeout node:internal/timers"}}],"socketOnDrain node:_http_server":[{"file":"node:_http_server","fn":"socketOnDrain","id":"47","ix":"0","pos":"23854","caller":{"file":"node:_http_server","fn":"updateOutgoingData","id":"47","ix":"-1","pos":"23741","key":"updateOutgoingData node:_http_server"}}],"get node:internal/streams/writable":[{"file":"node:internal/streams/writable","fn":"get","id":"47","ix":"1","pos":"24394","caller":{"file":"node:_http_server","fn":"updateOutgoingData","id":"47","ix":"-1","pos":"23741","key":"updateOutgoingData node:_http_server"}},{"file":"node:internal/streams/writable","fn":"get","id":"67","ix":"6","pos":"23031","caller":{"file":"node:_http_server","fn":"assignSocket","id":"67","ix":"-1","pos":"9954","key":"assignSocket node:_http_server"}},{"file":"node:internal/streams/writable","fn":"get","id":"76","ix":"1","pos":"23031","caller":{"file":"node:_http_outgoing","fn":"_send","id":"76","ix":"-1","pos":"10226","key":"_send node:_http_outgoing"}},{"file":"node:internal/streams/writable","fn":"get","id":"91","ix":"0","pos":"24394","caller":{"file":"node:_http_server","fn":"parserOnIncoming","id":"91","ix":"-1","pos":"31916","key":"parserOnIncoming node:_http_server"}},{"file":"node:internal/streams/writable","fn":"get","id":"101","ix":"1","pos":"24664","caller":{"file":"node:_http_outgoing","fn":"end","id":"101","ix":"-1","pos":"29396","key":"end node:_http_outgoing"}},{"file":"node:internal/streams/writable","fn":"get","id":"101","ix":"6","pos":"23031","caller":{"file":"node:_http_outgoing","fn":"end","id":"101","ix":"-1","pos":"29396","key":"end node:_http_outgoing"}},{"file":"node:internal/streams/writable","fn":"get","id":"102","ix":"5","pos":"23031","caller":{"file":"node:_http_outgoing","fn":"write_","id":"102","ix":"-1","pos":"25617","key":"write_ node:_http_outgoing"}}],"_addHeaderLine node:_http_incoming":[{"file":"node:_http_incoming","fn":"_addHeaderLine","id":"51","ix":"0","pos":"12926","caller":{"file":"node:_http_incoming","fn":"get","id":"51","ix":"-1","pos":"3268","key":"get node:_http_incoming"}}],"BufferList node:internal/streams/buffer_list":[{"file":"node:internal/streams/buffer_list","fn":"BufferList","id":"50","ix":"0","pos":"265","caller":{"file":"node:internal/streams/readable","fn":"ReadableState","id":"50","ix":"-1","pos":"2655","key":"ReadableState node:internal/streams/readable"}},{"file":"node:internal/streams/buffer_list","fn":"BufferList","id":"73","ix":"4","pos":"265","caller":{"file":"node:internal/streams/readable","fn":"Readable","id":"73","ix":"-1","pos":"6592","key":"Readable node:internal/streams/readable"}}],"getHighWaterMark node:internal/streams/state":[{"file":"node:internal/streams/state","fn":"getHighWaterMark","id":"50","ix":"1","pos":"826","caller":{"file":"node:internal/streams/readable","fn":"ReadableState","id":"50","ix":"-1","pos":"2655","key":"ReadableState node:internal/streams/readable"}},{"file":"node:internal/streams/state","fn":"getHighWaterMark","id":"73","ix":"6","pos":"826","caller":{"file":"node:internal/streams/readable","fn":"Readable","id":"73","ix":"-1","pos":"6592","key":"Readable node:internal/streams/readable"}}],"highWaterMarkFrom node:internal/streams/state":[{"file":"node:internal/streams/state","fn":"highWaterMarkFrom","id":"50","ix":"2","pos":"313","caller":{"file":"node:internal/streams/readable","fn":"ReadableState","id":"50","ix":"-1","pos":"2655","key":"ReadableState node:internal/streams/readable"}},{"file":"node:internal/streams/state","fn":"highWaterMarkFrom","id":"73","ix":"7","pos":"313","caller":{"file":"node:internal/streams/readable","fn":"Readable","id":"73","ix":"-1","pos":"6592","key":"Readable node:internal/streams/readable"}}],"Stream node:internal/streams/legacy":[{"file":"node:internal/streams/legacy","fn":"Stream","id":"55","ix":"0","pos":"127","caller":{"file":"node:_http_outgoing","fn":"OutgoingMessage","id":"55","ix":"-1","pos":"3478","key":"OutgoingMessage node:_http_outgoing"}},{"file":"node:internal/streams/legacy","fn":"Stream","id":"73","ix":"0","pos":"127","caller":{"file":"node:internal/streams/readable","fn":"Readable","id":"73","ix":"-1","pos":"6592","key":"Readable node:internal/streams/readable"}}],"EventEmitter node:events":[{"file":"node:events","fn":"EventEmitter","id":"55","ix":"1","pos":"6441","caller":{"file":"node:_http_outgoing","fn":"OutgoingMessage","id":"55","ix":"-1","pos":"3478","key":"OutgoingMessage node:_http_outgoing"}},{"file":"node:events","fn":"EventEmitter","id":"73","ix":"1","pos":"6441","caller":{"file":"node:internal/streams/readable","fn":"Readable","id":"73","ix":"-1","pos":"6592","key":"Readable node:internal/streams/readable"}}],"getDefaultHighWaterMark node:internal/streams/state":[{"file":"node:internal/streams/state","fn":"getDefaultHighWaterMark","id":"55","ix":"2","pos":"488","caller":{"file":"node:_http_outgoing","fn":"OutgoingMessage","id":"55","ix":"-1","pos":"3478","key":"OutgoingMessage node:_http_outgoing"}}],"EventEmitter.init node:events":[{"file":"node:events","fn":"EventEmitter.init","id":"55","ix":"3","pos":"9772","caller":{"file":"node:_http_outgoing","fn":"OutgoingMessage","id":"55","ix":"-1","pos":"3478","key":"OutgoingMessage node:_http_outgoing"}},{"file":"node:events","fn":"EventEmitter.init","id":"73","ix":"5","pos":"9772","caller":{"file":"node:internal/streams/readable","fn":"Readable","id":"73","ix":"-1","pos":"6592","key":"Readable node:internal/streams/readable"}}],"howMuchToRead node:internal/streams/readable":[{"file":"node:internal/streams/readable","fn":"howMuchToRead","id":"56","ix":"1","pos":"12610","caller":{"file":"node:internal/streams/readable","fn":"Readable.read","id":"56","ix":"-1","pos":"13087","key":"Readable.read node:internal/streams/readable"}}],"_destroy node:_http_incoming":[{"file":"node:_http_incoming","fn":"_destroy","id":"57","ix":"0","pos":"6374","caller":{"file":"node:internal/streams/destroy","fn":"_destroy","id":"57","ix":"-1","pos":"1587","key":"_destroy node:internal/streams/destroy"}}],"get node:internal/streams/readable":[{"file":"node:internal/streams/readable","fn":"get","id":"57","ix":"1","pos":"38284","caller":{"file":"node:internal/streams/destroy","fn":"_destroy","id":"57","ix":"-1","pos":"1587","key":"_destroy node:internal/streams/destroy"}},{"file":"node:internal/streams/readable","fn":"get","id":"66","ix":"0","pos":"38284","caller":{"file":"node:_http_server","fn":"clearIncoming","id":"66","ix":"-1","pos":"29948","key":"clearIncoming node:_http_server"}},{"file":"node:internal/streams/readable","fn":"get","id":"90","ix":"0","pos":"36527","caller":{"file":"node:_http_incoming","fn":"IncomingMessage","id":"90","ix":"-1","pos":"1906","key":"IncomingMessage node:_http_incoming"}},{"file":"node:internal/streams/readable","fn":"get","id":"92","ix":"2","pos":"36527","caller":{"file":"node:_http_common","fn":"parserOnHeadersComplete","id":"92","ix":"-1","pos":"2790","key":"parserOnHeadersComplete node:_http_common"}},{"file":"node:internal/streams/readable","fn":"get","id":"94","ix":"9","pos":"38284","caller":{"file":"node:_http_server","fn":"resOnFinish","id":"94","ix":"-1","pos":"30286","key":"resOnFinish node:_http_server"}},{"file":"node:internal/streams/readable","fn":"get","id":"96","ix":"0","pos":"35473","caller":{"file":"node:_http_incoming","fn":"readStart","id":"96","ix":"-1","pos":"1666","key":"readStart node:_http_incoming"}}],"get node:internal/streams/duplex":[{"file":"node:internal/streams/duplex","fn":"get","id":"57","ix":"2","pos":"3814","caller":{"file":"node:internal/streams/destroy","fn":"_destroy","id":"57","ix":"-1","pos":"1587","key":"_destroy node:internal/streams/destroy"}},{"file":"node:internal/streams/duplex","fn":"get","id":"65","ix":"3","pos":"3814","caller":{"file":"node:internal/streams/writable","fn":"afterWriteTick","id":"65","ix":"-1","pos":"15324","key":"afterWriteTick node:internal/streams/writable"}},{"file":"node:internal/streams/duplex","fn":"get","id":"76","ix":"2","pos":"3814","caller":{"file":"node:_http_outgoing","fn":"_send","id":"76","ix":"-1","pos":"10226","key":"_send node:_http_outgoing"}},{"file":"node:internal/streams/duplex","fn":"get","id":"101","ix":"7","pos":"3814","caller":{"file":"node:_http_outgoing","fn":"end","id":"101","ix":"-1","pos":"29396","key":"end node:_http_outgoing"}},{"file":"node:internal/streams/duplex","fn":"get","id":"102","ix":"6","pos":"3814","caller":{"file":"node:_http_outgoing","fn":"write_","id":"102","ix":"-1","pos":"25617","key":"write_ node:_http_outgoing"}}],"_write node:internal/streams/writable":[{"file":"node:internal/streams/writable","fn":"_write","id":"60","ix":"0","pos":"9615","caller":{"file":"node:internal/streams/writable","fn":"Writable.write","id":"60","ix":"-1","pos":"10981","key":"Writable.write node:internal/streams/writable"}},{"file":"node:internal/streams/writable","fn":"_write","id":"88","ix":"2","pos":"9615","caller":{"file":"node:_http_outgoing","fn":"_flushOutput","id":"88","ix":"-1","pos":"32880","key":"_flushOutput node:_http_outgoing"}}],"writeOrBuffer node:internal/streams/writable":[{"file":"node:internal/streams/writable","fn":"writeOrBuffer","id":"60","ix":"1","pos":"11900","caller":{"file":"node:internal/streams/writable","fn":"Writable.write","id":"60","ix":"-1","pos":"10981","key":"Writable.write node:internal/streams/writable"}},{"file":"node:internal/streams/writable","fn":"writeOrBuffer","id":"88","ix":"3","pos":"11900","caller":{"file":"node:_http_outgoing","fn":"_flushOutput","id":"88","ix":"-1","pos":"32880","key":"_flushOutput node:_http_outgoing"}}],"isEncoding node:buffer":[{"file":"node:buffer","fn":"isEncoding","id":"60","ix":"2","pos":"16099","caller":{"file":"node:internal/streams/writable","fn":"Writable.write","id":"60","ix":"-1","pos":"10981","key":"Writable.write node:internal/streams/writable"}},{"file":"node:buffer","fn":"isEncoding","id":"88","ix":"4","pos":"16099","caller":{"file":"node:_http_outgoing","fn":"_flushOutput","id":"88","ix":"-1","pos":"32880","key":"_flushOutput node:_http_outgoing"}}],"normalizeEncoding node:internal/util":[{"file":"node:internal/util","fn":"normalizeEncoding","id":"60","ix":"3","pos":"5589","caller":{"file":"node:internal/streams/writable","fn":"Writable.write","id":"60","ix":"-1","pos":"10981","key":"Writable.write node:internal/streams/writable"}},{"file":"node:internal/util","fn":"normalizeEncoding","id":"88","ix":"5","pos":"5589","caller":{"file":"node:_http_outgoing","fn":"_flushOutput","id":"88","ix":"-1","pos":"32880","key":"_flushOutput node:_http_outgoing"}}],"destroy node:internal/streams/destroy":[{"file":"node:internal/streams/destroy","fn":"destroy","id":"62","ix":"1","pos":"797","caller":{"file":"node:internal/streams/readable","fn":"endReadableNT","id":"62","ix":"-1","pos":"39856","key":"endReadableNT node:internal/streams/readable"}}],"checkError node:internal/streams/destroy":[{"file":"node:internal/streams/destroy","fn":"checkError","id":"62","ix":"4","pos":"379","caller":{"file":"node:internal/streams/readable","fn":"endReadableNT","id":"62","ix":"-1","pos":"39856","key":"endReadableNT node:internal/streams/readable"}}],"afterWrite node:internal/streams/writable":[{"file":"node:internal/streams/writable","fn":"afterWrite","id":"65","ix":"0","pos":"15461","caller":{"file":"node:internal/streams/writable","fn":"afterWriteTick","id":"65","ix":"-1","pos":"15324","key":"afterWriteTick node:internal/streams/writable"}}],"finishMaybe node:internal/streams/writable":[{"file":"node:internal/streams/writable","fn":"finishMaybe","id":"65","ix":"1","pos":"21278","caller":{"file":"node:internal/streams/writable","fn":"afterWriteTick","id":"65","ix":"-1","pos":"15324","key":"afterWriteTick node:internal/streams/writable"}}],"needFinish node:internal/streams/writable":[{"file":"node:internal/streams/writable","fn":"needFinish","id":"65","ix":"2","pos":"19680","caller":{"file":"node:internal/streams/writable","fn":"afterWriteTick","id":"65","ix":"-1","pos":"15324","key":"afterWriteTick node:internal/streams/writable"}}],"Readable.removeListener node:internal/streams/readable":[{"file":"node:internal/streams/readable","fn":"Readable.removeListener","id":"68","ix":"1","pos":"29255","caller":{"file":"node:_http_server","fn":"detachSocket","id":"68","ix":"-1","pos":"10209","key":"detachSocket node:_http_server"}}],"removeListener node:events":[{"file":"node:events","fn":"removeListener","id":"68","ix":"2","pos":"19479","caller":{"file":"node:_http_server","fn":"detachSocket","id":"68","ix":"-1","pos":"10209","key":"detachSocket node:_http_server"}}],"spliceOne node:internal/util":[{"file":"node:internal/util","fn":"spliceOne","id":"68","ix":"3","pos":"12661","caller":{"file":"node:_http_server","fn":"detachSocket","id":"68","ix":"-1","pos":"10209","key":"detachSocket node:_http_server"}}],"Readable.on node:internal/streams/readable":[{"file":"node:internal/streams/readable","fn":"Readable.on","id":"67","ix":"5","pos":"28253","caller":{"file":"node:_http_server","fn":"assignSocket","id":"67","ix":"-1","pos":"9954","key":"assignSocket node:_http_server"}}],"refresh node:internal/timers":[{"file":"node:internal/timers","fn":"refresh","id":"70","ix":"0","pos":"7266","caller":{"file":"node:net","fn":"_unrefTimer","id":"70","ix":"-1","pos":"13724","key":"_unrefTimer node:net"}}],"unrefActive node:internal/timers":[{"file":"node:internal/timers","fn":"unrefActive","id":"70","ix":"1","pos":"10042","caller":{"file":"node:net","fn":"_unrefTimer","id":"70","ix":"-1","pos":"13724","key":"_unrefTimer node:net"}}],"insertGuarded node:internal/timers":[{"file":"node:internal/timers","fn":"insertGuarded","id":"70","ix":"2","pos":"10325","caller":{"file":"node:net","fn":"_unrefTimer","id":"70","ix":"-1","pos":"13724","key":"_unrefTimer node:net"}}],"utcDate node:internal/http":[{"file":"node:internal/http","fn":"utcDate","id":"74","ix":"0","pos":"365","caller":{"file":"node:_http_outgoing","fn":"_storeHeader","id":"74","ix":"-1","pos":"12144","key":"_storeHeader node:_http_outgoing"}}],"construct node:internal/streams/destroy":[{"file":"node:internal/streams/destroy","fn":"construct","id":"73","ix":"2","pos":"4433","caller":{"file":"node:internal/streams/readable","fn":"Readable","id":"73","ix":"-1","pos":"6592","key":"Readable node:internal/streams/readable"}}],"ReadableState node:internal/streams/readable":[{"file":"node:internal/streams/readable","fn":"ReadableState","id":"73","ix":"3","pos":"2655","caller":{"file":"node:internal/streams/readable","fn":"Readable","id":"73","ix":"-1","pos":"6592","key":"Readable node:internal/streams/readable"}}],"checkInvalidHeaderChar node:_http_common":[{"file":"node:_http_common","fn":"checkInvalidHeaderChar","id":"75","ix":"0","pos":"7041","caller":{"file":"node:_http_server","fn":"writeHead","id":"75","ix":"-1","pos":"11412","key":"writeHead node:_http_server"}}],"_writeRaw node:_http_outgoing":[{"file":"node:_http_outgoing","fn":"_writeRaw","id":"76","ix":"0","pos":"11233","caller":{"file":"node:_http_outgoing","fn":"_send","id":"76","ix":"-1","pos":"10226","key":"_send node:_http_outgoing"}},{"file":"node:_http_outgoing","fn":"_writeRaw","id":"101","ix":"5","pos":"11233","caller":{"file":"node:_http_outgoing","fn":"end","id":"101","ix":"-1","pos":"29396","key":"end node:_http_outgoing"}},{"file":"node:_http_outgoing","fn":"_writeRaw","id":"102","ix":"4","pos":"11233","caller":{"file":"node:_http_outgoing","fn":"write_","id":"102","ix":"-1","pos":"25617","key":"write_ node:_http_outgoing"}}],"clearBuffer node:internal/streams/writable":[{"file":"node:internal/streams/writable","fn":"clearBuffer","id":"78","ix":"0","pos":"16536","caller":{"file":"node:internal/streams/writable","fn":"Writable.uncork","id":"78","ix":"-1","pos":"11173","key":"Writable.uncork node:internal/streams/writable"}}],"resetBuffer node:internal/streams/writable":[{"file":"node:internal/streams/writable","fn":"resetBuffer","id":"78","ix":"1","pos":"7207","caller":{"file":"node:internal/streams/writable","fn":"Writable.uncork","id":"78","ix":"-1","pos":"11173","key":"Writable.uncork node:internal/streams/writable"}}],"doWrite node:internal/streams/writable":[{"file":"node:internal/streams/writable","fn":"doWrite","id":"78","ix":"2","pos":"12909","caller":{"file":"node:internal/streams/writable","fn":"Writable.uncork","id":"78","ix":"-1","pos":"11173","key":"Writable.uncork node:internal/streams/writable"}}],"Socket._writev node:net":[{"file":"node:net","fn":"Socket._writev","id":"78","ix":"3","pos":"24753","caller":{"file":"node:internal/streams/writable","fn":"Writable.uncork","id":"78","ix":"-1","pos":"11173","key":"Writable.uncork node:internal/streams/writable"}}],"Socket._writeGeneric node:net":[{"file":"node:net","fn":"Socket._writeGeneric","id":"78","ix":"4","pos":"23810","caller":{"file":"node:internal/streams/writable","fn":"Writable.uncork","id":"78","ix":"-1","pos":"11173","key":"Writable.uncork node:internal/streams/writable"}}],"get node:net":[{"file":"node:net","fn":"get","id":"78","ix":"5","pos":"61696","caller":{"file":"node:internal/streams/writable","fn":"Writable.uncork","id":"78","ix":"-1","pos":"11173","key":"Writable.uncork node:internal/streams/writable"}}],"Readable.resume node:internal/streams/readable":[{"file":"node:internal/streams/readable","fn":"Readable.resume","id":"79","ix":"0","pos":"31274","caller":{"file":"node:net","fn":"Socket.resume","id":"79","ix":"-1","pos":"19778","key":"Socket.resume node:net"}},{"file":"node:internal/streams/readable","fn":"Readable.resume","id":"81","ix":"0","pos":"31274","caller":{"file":"node:_http_incoming","fn":"_dump","id":"81","ix":"-1","pos":"14358","key":"_dump node:_http_incoming"}}],"Readable.removeAllListeners node:internal/streams/readable":[{"file":"node:internal/streams/readable","fn":"Readable.removeAllListeners","id":"81","ix":"2","pos":"29923","caller":{"file":"node:_http_incoming","fn":"_dump","id":"81","ix":"-1","pos":"14358","key":"_dump node:_http_incoming"}}],"removeAllListeners node:events":[{"file":"node:events","fn":"removeAllListeners","id":"81","ix":"3","pos":"21098","caller":{"file":"node:_http_incoming","fn":"_dump","id":"81","ix":"-1","pos":"14358","key":"_dump node:_http_incoming"}}],"flow node:internal/streams/readable":[{"file":"node:internal/streams/readable","fn":"flow","id":"82","ix":"1","pos":"32309","caller":{"file":"node:internal/streams/readable","fn":"emitReadable_","id":"82","ix":"-1","pos":"18942","key":"emitReadable_ node:internal/streams/readable"}},{"file":"node:internal/streams/readable","fn":"flow","id":"93","ix":"1","pos":"32309","caller":{"file":"node:internal/streams/readable","fn":"resume_","id":"93","ix":"-1","pos":"31762","key":"resume_ node:internal/streams/readable"}}],"runNextTicks node:internal/process/task_queues":[{"file":"node:internal/process/task_queues","fn":"runNextTicks","id":"87","ix":"8","pos":"1268","caller":{"file":"node:internal/timers","fn":"listOnTimeout","id":"87","ix":"-1","pos":"15529","key":"listOnTimeout node:internal/timers"}}],"_addHeaderLines node:_http_incoming":[{"file":"node:_http_incoming","fn":"_addHeaderLines","id":"92","ix":"0","pos":"7241","caller":{"file":"node:_http_common","fn":"parserOnHeadersComplete","id":"92","ix":"-1","pos":"2790","key":"parserOnHeadersComplete node:_http_common"}}],"IncomingMessage node:_http_incoming":[{"file":"node:_http_incoming","fn":"IncomingMessage","id":"92","ix":"1","pos":"1906","caller":{"file":"node:_http_common","fn":"parserOnHeadersComplete","id":"92","ix":"-1","pos":"2790","key":"parserOnHeadersComplete node:_http_common"}}],"get hasSubscribers node:diagnostics_channel":[{"file":"node:diagnostics_channel","fn":"get hasSubscribers","id":"91","ix":"1","pos":"4353","caller":{"file":"node:_http_server","fn":"parserOnIncoming","id":"91","ix":"-1","pos":"31916","key":"parserOnIncoming node:_http_server"}},{"file":"node:diagnostics_channel","fn":"get hasSubscribers","id":"94","ix":"0","pos":"4353","caller":{"file":"node:_http_server","fn":"resOnFinish","id":"94","ix":"-1","pos":"30286","key":"resOnFinish node:_http_server"}}],"ServerResponse node:_http_server":[{"file":"node:_http_server","fn":"ServerResponse","id":"91","ix":"4","pos":"7111","caller":{"file":"node:_http_server","fn":"parserOnIncoming","id":"91","ix":"-1","pos":"31916","key":"parserOnIncoming node:_http_server"}}],"hasObserver node:internal/perf/observe":[{"file":"node:internal/perf/observe","fn":"hasObserver","id":"91","ix":"5","pos":"15924","caller":{"file":"node:_http_server","fn":"parserOnIncoming","id":"91","ix":"-1","pos":"31916","key":"parserOnIncoming node:_http_server"}}],"isTraceHTTPEnabled node:internal/http":[{"file":"node:internal/http","fn":"isTraceHTTPEnabled","id":"91","ix":"6","pos":"739","caller":{"file":"node:_http_server","fn":"parserOnIncoming","id":"91","ix":"-1","pos":"31916","key":"parserOnIncoming node:_http_server"}}],"resetSocketTimeout node:_http_server":[{"file":"node:_http_server","fn":"resetSocketTimeout","id":"91","ix":"7","pos":"35361","caller":{"file":"node:_http_server","fn":"parserOnIncoming","id":"91","ix":"-1","pos":"31916","key":"parserOnIncoming node:_http_server"}}],"getObserverType node:internal/perf/observe":[{"file":"node:internal/perf/observe","fn":"getObserverType","id":"91","ix":"8","pos":"2907","caller":{"file":"node:_http_server","fn":"parserOnIncoming","id":"91","ix":"-1","pos":"31916","key":"parserOnIncoming node:_http_server"}}],"clearIncoming node:_http_server":[{"file":"node:_http_server","fn":"clearIncoming","id":"94","ix":"8","pos":"29948","caller":{"file":"node:_http_server","fn":"resOnFinish","id":"94","ix":"-1","pos":"30286","key":"resOnFinish node:_http_server"}}],"afterWriteDispatched node:internal/stream_base_commons":[{"file":"node:internal/stream_base_commons","fn":"afterWriteDispatched","id":"99","ix":"0","pos":"3815","caller":{"file":"node:internal/stream_base_commons","fn":"writevGeneric","id":"99","ix":"-1","pos":"2960","key":"writevGeneric node:internal/stream_base_commons"}}],"createWriteWrap node:internal/stream_base_commons":[{"file":"node:internal/stream_base_commons","fn":"createWriteWrap","id":"99","ix":"1","pos":"2722","caller":{"file":"node:internal/stream_base_commons","fn":"writevGeneric","id":"99","ix":"-1","pos":"2960","key":"writevGeneric node:internal/stream_base_commons"}}],"get node:_http_outgoing":[{"file":"node:_http_outgoing","fn":"get","id":"101","ix":"0","pos":"5687","caller":{"file":"node:_http_outgoing","fn":"end","id":"101","ix":"-1","pos":"29396","key":"end node:_http_outgoing"}}],"_send node:_http_outgoing":[{"file":"node:_http_outgoing","fn":"_send","id":"101","ix":"3","pos":"10226","caller":{"file":"node:_http_outgoing","fn":"end","id":"101","ix":"-1","pos":"29396","key":"end node:_http_outgoing"}},{"file":"node:_http_outgoing","fn":"_send","id":"102","ix":"2","pos":"10226","caller":{"file":"node:_http_outgoing","fn":"write_","id":"102","ix":"-1","pos":"25617","key":"write_ node:_http_outgoing"}}],"strictContentLength node:_http_outgoing":[{"file":"node:_http_outgoing","fn":"strictContentLength","id":"101","ix":"4","pos":"25394","caller":{"file":"node:_http_outgoing","fn":"end","id":"101","ix":"-1","pos":"29396","key":"end node:_http_outgoing"}}],"_implicitHeader node:_http_server":[{"file":"node:_http_server","fn":"_implicitHeader","id":"102","ix":"0","pos":"11302","caller":{"file":"node:_http_outgoing","fn":"write_","id":"102","ix":"-1","pos":"25617","key":"write_ node:_http_outgoing"}}],"byteLength node:buffer":[{"file":"node:buffer","fn":"byteLength","id":"102","ix":"3","pos":"23087","caller":{"file":"node:_http_outgoing","fn":"write_","id":"102","ix":"-1","pos":"25617","key":"write_ node:_http_outgoing"}}]}}